[
    {
        "page_content": "标题“图表34：美国冷冻食品市场占比情况”的饼图展示了美国冷冻食品市场在不同销售渠道中的分布情况。该饼图将市场划分为四个主要部分，每个部分用不同颜色表示，并标注了对应的类别和所占百分比：\n\n1. **餐饮服务企业**：占比最大，为39%，以蓝色表示。这部分代表冷冻食品在餐厅、酒店、食堂等餐饮机构中的使用量，是当前美国冷冻食品市场最主要的消费渠道。\n\n2. **商超批发**：占比26%，以橙色表示。指通过超市、连锁便利店以及批发商等零售终端销售的冷冻食品，是第二大销售渠道。\n\n3. **零售**：占比23%，以灰色表示。通常指消费者直接在零售商店购买的冷冻食品，包括独立超市、杂货店等。\n\n4. **出口**：占比12%，以黄色表示。代表美国冷冻食品出口到其他国家的市场份额，虽然比例相对较小，但仍是市场的重要组成部分。\n\n整体来看，该饼图清晰地反映出美国冷冻食品市场以B端（企业端）为主导，其中餐饮服务企业占据近四成份额，而C端（消费者端）则由商超批发和零售共同构成，合计占比接近50%。出口部分虽小，也体现了美国冷冻食品的国际竞争力。",
        "metadata": {
            "filename": "千味央厨-百味千寻餐饮供应链龙头正崛起-21091628页.pdf",
            "page": 17,
            "type": "image",
            "img_path": "images/d50ecb2944c30ae1bb85b73893839fd9f5c3e9b192d6b562eb4bb779dac2755c.jpg",
            "table_body": "None"
        }
    },
    {
        "page_content": "标题为“图表35：美国冷冻食品C端CR4为36%”的饼图展示了美国冷冻食品消费端（C端）市场的主要企业市场份额分布情况。该图表通过不同颜色的扇形区域表示各企业在市场中的占比，具体信息如下：\n\n- **ConAgra**：占据12%的市场份额，以蓝色表示，是市场份额最大的单一企业。\n- **Schwan's**：占10%，用橙色表示，位居第二。\n- **Lamb Weston**：占8%，以灰色表示，排名第三。\n- **Nestle**：占6%，以黄色表示，位列第四。\n- **其他企业**：合计占64%，以深蓝色表示，代表除上述四家之外的所有其他竞争者。\n\n从数据可以看出，美国冷冻食品C端市场的集中度相对较低，前四大企业的合计市场份额（CR4）为36%（即12% + 10% + 8% + 6% = 36%），说明市场仍处于较为分散的状态，头部企业虽有一定优势，但大量中小品牌共同占据了大部分市场空间。这表明该行业竞争激烈，且存在较大的市场进入机会和品牌多元化特征。",
        "metadata": {
            "filename": "千味央厨-百味千寻餐饮供应链龙头正崛起-21091628页.pdf",
            "page": 17,
            "type": "image",
            "img_path": "images/f0a00e80b690cbfd2f4e4b547444b57c45a567f8a0f156942b615f53394de03a.jpg",
            "table_body": "None"
        }
    },
    {
        "page_content": "标题为“图表36：SYSC0主营业务结构”的柱状图展示了某公司在2019财年（FY2019）、2020财年（FY2020）和2021财年（FY2021）三个年度的主营业务收入构成情况，以百分比形式呈现各业务板块在总收入中的占比。\n\n该图采用**堆叠柱状图**的形式，每一年份对应一个总高度为100%的柱子，由不同颜色的条块组成，每个颜色代表一个具体的业务类别。图例位于左上角，说明了各颜色对应的业务类型：\n\n- **红色**：冷鲜/冷冻肉类  \n- **蓝色**：罐头/干制品  \n- **灰色**：冷冻水果、蔬菜、面包及其他  \n- **黄色**：家禽  \n- **绿色**：纸张及一次性用品  \n- **深蓝色**：奶制品  \n- **橙色**：海鲜  \n- **棕色**：饮料  \n- **浅灰色**：其他  \n\n从图中可以看出：\n\n1. **冷鲜/冷冻肉类**（红色）是公司最大的业务板块，在三年中均占据约20%-25%的份额，保持相对稳定。\n2. **罐头/干制品**（蓝色）和**冷冻水果、蔬菜、面包及其他**（灰色）也占较大比重，分别约为15%-20%左右，两者合计接近或超过30%。\n3. **家禽**（黄色）和**奶制品**（深蓝色）的占比相对较低，但有较为明显的存在感，家禽约占10%-15%，奶制品约5%-10%。\n4. **海鲜**（橙色）和**饮料**（棕色）的占比较小，通常低于5%。\n5. **纸张及一次性用品**（绿色）在三年中占比略有波动，但整体维持在5%-8%之间。\n6. “其他”类别（浅灰色）占比最小，基本在5%以下。\n\n总体来看，该公司的主营业务结构在三年间变化不大，呈现出以**冷鲜/冷冻肉类、罐头/干制品和冷冻果蔬类**为主的多元化布局。其中，前三大品类合计贡献了超过60%的收入，显示出较强的集中性。\n\n此图清晰地反映了SYSC0公司在近三年内主营业务的收入分布特征，有助于分析其核心业务优势与市场定位。",
        "metadata": {
            "filename": "千味央厨-百味千寻餐饮供应链龙头正崛起-21091628页.pdf",
            "page": 17,
            "type": "image",
            "img_path": "images/9cd5f7a293ed5acc09092c3a0743345dc3a48861620581cbbf8ef609f0054d19.jpg",
            "table_body": "None"
        }
    },
    {
        "page_content": "标题为“图表37：SYSC0近三年客户成分表”的图片是一张堆叠柱状图，展示了SYSC0公司在2019财年（FY2019）、2020财年（FY2020）和2021财年（FY2021）三个年度中，客户构成的行业分布情况。该图以百分比形式呈现各行业客户在总客户中的占比。\n\n图表的纵轴表示客户占比，从0%到100%，横轴代表三个财年：FY2019、FY2020和FY2021。每个柱子由不同颜色的区块堆叠而成，每种颜色代表一个特定行业类别，具体如下：\n\n- **红色**：餐饮\n- **蓝色**：医疗\n- **灰色**：教育及政府\n- **黄色**：旅游文娱\n- **深蓝色**：其他\n\n### 各年度客户构成分析：\n\n#### FY2019：\n- 餐饮行业占比最高，约为60%。\n- 医疗行业约占10%。\n- 教育及政府行业约8%。\n- 旅游文娱行业约5%。\n- 其他行业占比约17%。\n\n#### FY2020：\n- 餐饮行业仍占主导地位，比例略高于FY2019，约为62%。\n- 医疗行业略有增长，接近12%。\n- 教育及政府行业占比基本持平，约为8%。\n- 旅游文娱行业小幅下降，约为4%。\n- 其他行业占比约为14%。\n\n#### FY2021：\n- 餐饮行业继续保持最大份额，占比进一步上升至约65%。\n- 医疗行业占比稳定在约12%左右。\n- 教育及政府行业略有下降，约为7%。\n- 旅游文娱行业维持在约4%。\n- 其他行业占比略微回升至约12%。\n\n### 总体趋势：\n- 餐饮行业是SYSC0最主要的客户来源，在三年间持续增长，从60%提升至65%，显示出其在该领域的市场渗透力不断增强。\n- 医疗行业客户占比稳步提升，反映公司在医疗领域的业务拓展取得进展。\n- 教育及政府、旅游文娱行业客户占比相对稳定或略有下降，表明这些领域可能受外部环境影响较大（如疫情对旅游文娱的影响）。\n- “其他”类别的客户占比有所波动，但总体保持在10%-17%之间。\n\n综上所述，该图表清晰地反映了SYSC0公司客户结构以餐饮为主导，并在医疗领域逐步扩大影响力，整体客户构成趋于集中于少数几个关键行业。",
        "metadata": {
            "filename": "千味央厨-百味千寻餐饮供应链龙头正崛起-21091628页.pdf",
            "page": 17,
            "type": "image",
            "img_path": "images/e26c60c367b9d051f8844d87db598006fdc0f328e2056e3f19a36df66127a404.jpg",
            "table_body": "None"
        }
    },
    {
        "page_content": "以 SYSCO 为例，探讨美国最大餐饮供应链企业的成长路径。公司于1969 年成立，仅用1年时间便在纽交所上市，在全球12个国家拥有超过300 家配送中心，为餐饮企业、医疗及教育机构、政府及其他餐饮服务企业提供食材供应服务。2021财年营收512.98 亿美元，净利润为5.24亿美元，净利率同比下滑 $8 5 . 3 7 \\%$ o\n来源：公司公告，国联证券研究所注：2021 财年截止至7月3日来源：公司公告，国联证券研究所注：2021 财年截止至7月3日\n\n营收逐年稳定增长，净利阶段性波动后表现稳定。在2015 年之前，公司因养老计划与费用摊销，净利润持续下滑，后因与USFOODS 的合并进程违反美国反垄断法而被迫中止，净利润跌至新低，随着负面因素逐渐出清，盈利水平快速回升。\n",
        "metadata": {
            "filename": "千味央厨-百味千寻餐饮供应链龙头正崛起-21091628页.pdf",
            "page": 17,
            "type": "text",
            "img_path": "None",
            "table_body": "None"
        }
    }
]