[
    {
        "page_content": "这张表格的标题为 **“资产负债表”**，单位为**百万元人民币**，展示了某公司在 **2018年、2019年（实际数据，标记为A）以及2020年至2022年（预测数据，标记为E）** 的财务状况。以下是对该资产负债表内容的详细描述和分析：\n\n---\n\n### 一、资产结构\n\n#### 1. **流动资产**\n流动资产从2018年的 **2,770亿元** 增长至2022年预测的 **5,401亿元**，整体呈显著上升趋势。\n\n- **货币资金**：由2018年的2,212亿元增至2022年的3,846亿元，是流动资产的主要组成部分。2020年略有下降至2,094亿元，之后快速回升。\n- **应收及预付款项**：从2018年的324亿元增长到2022年的934亿元，反映出企业销售规模扩大或回款周期延长。\n- **存货**：金额较小，从2018年的9亿元逐步增长至2022年的36亿元，变化平稳。\n- **其他流动资产**：2018年为225亿元，2019年大幅下降至70亿元，但在2020年起回升并稳定在570–585亿元之间。\n\n> **小结**：流动资产的增长主要由货币资金和应收款项推动，说明公司现金流状况改善，但应收账款也有所增加，需关注回款效率。\n\n---\n\n#### 2. **非流动资产**\n非流动资产总体保持稳定增长，从2018年的 **2,836亿元** 增至2022年的 **3,382亿元**。\n\n- **长期股权投资**：从2018年的158亿元增至2019年的233亿元，并在后续年份维持不变。\n- **固定资产**：从819亿元（2018）增至893亿元（2022），呈缓慢增长趋势，反映企业持续进行产能投资。\n- **在建工程**：2018年仅为3亿元，2019年跃升至57亿元，此后保持稳定，表明新项目集中开工。\n- **无形资产**：从227亿元（2018）增长至529亿元（2020），随后略降，可能与摊销或估值调整有关。\n- **其他长期资产**：占比最大，从1,628亿元（2018）增至1,752亿元（2019），之后略有回落，但仍维持高位。\n\n> **小结**：非流动资产结构以“其他长期资产”为主，辅以固定资产和无形资产的增长，显示企业长期战略布局和资本投入。\n\n---\n\n#### 3. **资产总计**\n总资产从2018年的 **5,606亿元** 增长至2022年预测的 **8,782亿元**，增幅达56.6%，表明企业整体规模显著扩张。\n\n---\n\n### 二、负债结构\n\n#### 1. **流动负债**\n流动负债从2018年的 **1,329亿元** 大幅增长至2022年的 **3,635亿元**，增速较快。\n\n- **短期借款**：2018年为200亿元，2019年飙升至1,089亿元，但在2020年骤降至534亿元，2021–2022年清零，显示公司主动去杠杆。\n- **应付及预收款项**：从512亿元（2018）增长至2,143亿元（2022），持续上升，反映采购或经营性负债增加。\n- **其他流动负债**：从618亿元增至1,491亿元，增长显著，可能包括预提费用、短期债券等。\n\n> **小结**：尽管短期借款被逐步偿还，但整体流动负债仍在上升，主要源于经营性负债增长。\n\n---\n\n#### 2. **非流动负债**\n非流动负债从2018年的 **994亿元** 骤降至2019年及以后的 **9亿元**，几乎可以忽略。\n\n- **应付债券**：2018年为992亿元，之后归零，说明公司已偿还长期债券。\n- **长期借款**：始终为0。\n- **其他非流动负债**：保持在3–9亿元之间，影响较小。\n\n> **小结**：企业大幅削减长期债务，特别是债券融资，财务结构趋于保守。\n\n---\n\n#### 3. **负债合计**\n总负债从2018年的 **2,324亿元** 增至2022年的 **3,644亿元**，但增速低于资产增速，主要由流动负债中的经营性负债支撑。\n\n---\n\n### 三、股东权益\n\n#### 1. **股本**\n保持稳定，从2018年的1,127亿元增至2019年后的1,129亿元，基本不变。\n\n#### 2. **资本公积**\n从463亿元（2018）增至509亿元（2019起），之后稳定，可能因股权融资或资产评估增值。\n\n#### 3. **留存收益**\n从1,700亿元（2018）持续增长至2022年的3,418亿元，翻倍增长，反映盈利能力强且利润再投资比例高。\n\n#### 4. **归属母公司股东权益**\n从3,192亿元（2018）增长至4,978亿元（2022），年均复合增长率约11.6%。\n\n#### 5. **少数股东权益**\n从90亿元（2018）增至160亿元（2022），表明子公司中非全资控股部分权益增加。\n\n> **小结**：股东权益稳步增长，尤其是留存收益贡献显著，说明企业具备较强的盈利积累能力。\n\n---\n\n### 四、资产负债平衡\n\n- **负债和股东权益总计**：每年与“资产总计”完全相等（如2018年均为5,606亿元），符合会计恒等式：\n  \n  > **资产 = 负债 + 股东权益**\n\n  数据准确无误，账务平衡。\n\n---\n\n### 五、关键财务趋势总结\n\n| 指标 | 2018A | 2019A | 2020E | 2021E | 2022E | 变化趋势 |\n|------|-------|-------|-------|-------|-------|----------|\n| **总资产** | 5,606 | 6,167 | 6,642 | 7,355 | 8,782 | 快速增长 |\n| **总负债** | 2,324 | 2,818 | 2,923 | 3,021 | 3,644 | 温和增长 |\n| **股东权益** | 3,282 | 3,349 | 3,719 | 4,334 | 5,138 | 显著提升 |\n| **资产负债率**（负债/资产） | 41.4% | 45.7% | 44.0% | 41.1% | 41.5% | 先升后稳，维持在40%-46%区间 |\n\n> **资产负债率分析**：虽然2019年因短期借款上升导致负债率短暂上升，但随着债务偿还和权益积累，2020年后回落并保持稳定，财务风险可控。\n\n---\n\n### 六、结论\n\n该企业呈现出以下特征：\n\n1. **资产规模快速扩张**：五年内总资产增长超过50%，主要由货币资金、应收款项和长期资产驱动。\n2. **负债结构优化**：短期借款和债券被逐步清偿，长期负债极低，财务杠杆下降。\n3. **股东权益稳步增长**：依靠盈利积累（留存收益）实现内生增长，资本结构健康。\n4. **流动性充裕**：货币资金充足，流动比率（流动资产/流动负债）从2018年的2.08倍降至2022年的1.49倍，仍处于安全水平。\n5. **经营性负债上升**：应付及预收款项大幅增长，可能反映行业地位增强或供应链议价能力提高。\n\n---\n\n### 七、潜在关注点\n\n- **应收账款增长较快**：从324亿增至934亿，需关注坏账风险及现金流质量。\n- **其他流动资产和长期资产占比较高**：需进一步了解其具体构成，判断是否包含高风险或非核心资产。\n- **短期借款清零虽降低风险，但也可能影响财务灵活性**。\n\n---\n\n综上所述，这是一张展现企业**稳健扩张、去杠杆、盈利能力强**的资产负债表，财务状况总体良好，具备较强的可持续发展能力。",
        "metadata": {
            "filename": "公司研究广联达-造价业务转型加速推进施工业务整合效应初显-2020032615页.pdf",
            "page": 12,
            "type": "table",
            "img_path": "images/0cbad45c75aa71890832eec825f85abc65c089724790f55df6da4fde32c86772.jpg",
            "table_body": "<table><tr><td colspan=\"6\">至12月31日 2018A 2019A 2020E 2021E 2022E</td></tr><tr><td>流动资产</td><td>2,770</td><td>2,950</td><td>3,268</td><td>3,968</td><td>5,401</td></tr><tr><td>货币资金</td><td>2,212</td><td>2,231</td><td>2,094</td><td>2,617</td><td>3,846</td></tr><tr><td>应收及预付</td><td>324</td><td>628</td><td>591</td><td>751</td><td>934</td></tr><tr><td>存货</td><td>9</td><td>21</td><td>20</td><td>28</td><td>36</td></tr><tr><td>其他流动资产</td><td>225</td><td>70</td><td>562</td><td>573</td><td>585</td></tr><tr><td>非流动资产</td><td>2,836</td><td>3,217</td><td>3,375</td><td>3,387</td><td>3,382</td></tr><tr><td>长期股权投资</td><td>158</td><td>233</td><td>233</td><td>233</td><td>233</td></tr><tr><td>固定资产</td><td>819</td><td>803</td><td>843</td><td>873</td><td>893</td></tr><tr><td>在建工程</td><td>3</td><td>57</td><td>57</td><td>57</td><td>57</td></tr><tr><td>无形资产</td><td>227</td><td>373</td><td>529</td><td>521</td><td>506</td></tr><tr><td>其他长期资产</td><td>1,628</td><td>1,752</td><td>1,713</td><td>1,703</td><td>1,693</td></tr><tr><td>资产总计</td><td>5,606</td><td>6,167</td><td>6,642</td><td>7,355</td><td>8,782</td></tr><tr><td>流动负债</td><td>1,329</td><td>2,809</td><td>2,914</td><td>3,012</td><td>3,635</td></tr><tr><td>短期借款</td><td>200</td><td>1,089</td><td>534</td><td>0</td><td>0</td></tr><tr><td>应付及预收</td><td>512</td><td>1,068</td><td>1,515</td><td>1,856</td><td>2,143</td></tr><tr><td>其他流动负债</td><td>618</td><td>653</td><td>866</td><td>1,156</td><td>1,491</td></tr><tr><td>非流动负债</td><td>994</td><td>9</td><td>9</td><td>9</td><td>9</td></tr><tr><td>长期借款</td><td>0</td><td>0</td><td>0</td><td>0</td><td>0</td></tr><tr><td>应付债券</td><td>992</td><td>0</td><td>0</td><td>0</td><td>0</td></tr><tr><td>其他非流动负债</td><td>3</td><td>9</td><td>9</td><td>9</td><td>9</td></tr><tr><td>负债合计</td><td>2,324</td><td>2,818</td><td>2,923</td><td>3,021</td><td>3,644</td></tr><tr><td>股本</td><td>1,127</td><td>1,129</td><td>1,129</td><td>1,129</td><td>1,129</td></tr><tr><td>资本公积</td><td>463</td><td>509</td><td>509</td><td>509</td><td>509</td></tr><tr><td>留存收益</td><td>1,700</td><td>1,709</td><td>2,062</td><td>2,649</td><td>3,418</td></tr><tr><td>归属母公司股东权益</td><td>3,192</td><td>3,269</td><td>3,623</td><td>4,210</td><td>4,978</td></tr><tr><td>少数股东权益</td><td>90</td><td>80</td><td>96</td><td>124</td><td>160</td></tr><tr><td>负债和股东权益</td><td>5,606</td><td>6,167</td><td>6,642</td><td>7,355</td><td>8,782</td></tr></table>"
        }
    },
    {
        "page_content": "该表格为一份**利润表**（Income Statement），单位为**百万元人民币**，列示了某公司从2018年至2022年的财务数据，其中：\n\n- **2018A** 和 **2019A** 表示实际已发生的财务年度数据（Actual）；\n- **2020E、2021E、2022E** 表示未来年度的预测或估计值（Estimated/Forecasted）。\n\n---\n\n### 一、总体结构与时间范围\n\n| 项目 | 2018A | 2019A | 2020E | 2021E | 2022E |\n|------|------|------|------|------|------|\n| 报告周期 | 至12月31日 | 至12月31日 | 至12月31日 | 至12月31日 | 至12月31日 |\n\n说明：每年均为完整会计年度，截止日期为12月31日。\n\n---\n\n### 二、主要财务项目分析\n\n#### 1. **营业收入（Revenue）**\n- 逐年稳步增长：\n  - 2018年：2,904 亿元\n  - 2019年：3,541 亿元（同比增长约21.9%）\n  - 2020E：4,380 亿元（+23.7%）\n  - 2021E：5,537 亿元（+26.4%）\n  - 2022E：6,864 亿元（+23.9%）\n- **趋势**：持续高速增长，复合年增长率（CAGR）约为24%（2018–2022E）。\n\n#### 2. **营业成本（Cost of Goods Sold）**\n- 从188亿元增长至864亿元，虽绝对值较低，但增速较快：\n  - 2018A：188\n  - 2019A：371（+97.3%）\n  - 2020E：496（+33.7%）\n  - 2021E：667（+34.5%）\n  - 2022E：864（+29.5%）\n- **毛利率趋势**（粗略估算）：\n  - 2018年：(2904 - 188)/2904 ≈ **93.5%**\n  - 2019年：(3541 - 371)/3541 ≈ **89.5%**\n  - 2022E：(6864 - 864)/6864 ≈ **87.4%**\n- **结论**：尽管收入快速增长，毛利率略有下降，但仍维持在较高水平，可能属于轻资产或高附加值行业（如软件、互联网、生物科技等）。\n\n#### 3. **营业税金及附加**\n- 数值较小，变化平稳：\n  - 从45增至83亿元，增幅合理，与收入增长基本匹配。\n\n#### 4. **销售费用（Selling Expenses）**\n- 显著上升：\n  - 2018A：793\n  - 2019A：1,102（+38.9%）\n  - 2022E：1,853（较2018年翻倍以上）\n- 占收入比例：\n  - 2018年：793 / 2904 ≈ **27.3%**\n  - 2022E：1853 / 6864 ≈ **27.0%**\n- **结论**：销售投入持续加大，且占比稳定，显示公司重视市场推广。\n\n#### 5. **管理费用（Administrative Expenses）**\n- 持续增长：\n  - 2018A：765\n  - 2019A：820（+7.2%）\n  - 2022E：1,476（+93% 相比2018年）\n- 占收入比：\n  - 2018年：26.3%\n  - 2022E：21.5%\n- **结论**：管理效率略有提升，费用增速略低于收入增速。\n\n#### 6. **研发费用（R&D Expenses）**\n- 数据存在异常或格式错误：\n  - 2018A：727.17\n  - 2019A–2022E为空，但在2021E单元格中出现多个数值：“969.11 1182.52 1467.21 1784.53”\n- **推测**：可能是排版错误，实际应为：\n  - 2021E：969.11\n  - 2022E：1182.52（或更高）\n  - 后续两个数值可能属于更远期预测或不同情景\n- 若按此解读，研发费用显著增长，2022E可能达约1183亿元，占收入比例约17.2%，说明公司高度重视技术创新，可能为科技、医药或高端制造类企业。\n\n#### 7. **财务费用（Financial Expenses）**\n- 较低且呈下降趋势：\n  - 2018A：34.64\n  - 2022E：13.68\n- 表明融资成本较低，或债务结构优化，利息支出减少。\n\n#### 8. **资产减值损失（Impairment Losses）**\n- 波动较大：\n  - 2018A：55.81\n  - 2019A：-6.11（即为资产增值收益）\n  - 2020E：93.34（大幅增加）\n  - 2022E：78.14\n- 需关注是否存在大额资产减值风险。\n\n#### 9. **公允价值变动收益**\n- 始终为0，说明公司未持有重大以公允价值计量的金融资产。\n\n#### 10. **投资净收益（Net Investment Income）**\n- 稳定在20–22亿元之间，对利润贡献较小。\n\n#### 11. **营业利润（Operating Profit）**\n- 变化趋势：\n  - 2018A：484.56\n  - 2019A：290.37（同比下降40%）\n  - 2020E：413.71（回升）\n  - 2021E：687.99（+66%）\n  - 2022E：899.00（+30.4%）\n- **原因分析**：2019年营业利润大幅下滑，可能由于销售费用和管理费用上升、资产减值等因素；后续恢复增长，盈利能力改善。\n\n#### 12. **营业外收支**\n- 小额负值，每年约-2至-7亿元，对公司整体影响有限。\n\n#### 13. **利润总额（Total Profit Before Tax）**\n- 趋势与营业利润一致：\n  - 2018A：482\n  - 2019A：284（腰斩）\n  - 2020E：412\n  - 2021E：685\n  - 2022E：897\n\n#### 14. **所得税（Income Tax）**\n- 逐年上升，但税率相对稳定：\n  - 所得税/利润总额 ≈ 10%-11%，远低于标准25%企业所得税率\n  - **推测**：公司享受税收优惠政策（如高新技术企业、西部大开发优惠、研发加计扣除等）\n\n#### 15. **净利润（Net Profit）**\n- 净利润走势：\n  - 2018A：433\n  - 2019A：255（-41%）\n  - 2020E：369（+44.7%）\n  - 2021E：615（+66.7%）\n  - 2022E：805（+30.9%）\n- 显示公司盈利能力在2019年受挫后强劲反弹。\n\n#### 16. **少数股东损益（Minority Interest）**\n- 逐年上升：\n  - 2018A：-6（即少数股东亏损）\n  - 2019A起转正，2022E达36亿元\n- 说明子公司中非全资控股部分盈利增强。\n\n#### 17. **归属母公司净利润（Net Profit Attributable to Parent Company）**\n- 核心盈利指标：\n  - 2018A：439\n  - 2019A：235（-46.5%）\n  - 2020E：353（+50.2%）\n  - 2021E：587（+66.3%）\n  - 2022E：768（+30.8%）\n- **复合增长率（2018–2022E）**：约15.3%\n- **结论**：长期盈利能力强，未来预期良好。\n\n#### 18. **EBITDA（息税折旧摊销前利润）**\n- 反映经营现金流能力：\n  - 2018A：459.74\n  - 2019A：341.36（下降）\n  - 2020E：472.37\n  - 2021E：722.94\n  - 2022E：948.02\n- 增长迅速，2022E是2018年的两倍以上，表明核心业务现金流强劲。\n\n#### 19. **EPS（每股收益，元）**\n- 每股盈利：\n  - 2018A：0.39\n  - 2019A：0.21（腰斩）\n  - 2020E：0.31\n  - 2021E：0.52（+67.7%）\n  - 2022E：0.68（+30.8%）\n- EPS恢复并超越前期高点，对股价有积极支撑作用。\n\n---\n\n### 三、综合分析与观察要点\n\n| 维度 | 分析结论 |\n|------|----------|\n| **成长性** | 营业收入和净利润均保持高速增长，尤其2020年后加速，具备高成长潜力。 |\n| **盈利能力** | 尽管2019年出现短期下滑，但随后迅速恢复，毛利率、EBITDA、净利润率均表现优异。 |\n| **费用控制** | 销售与管理费用随规模扩张而上升，但占比趋于稳定或略降，控制较好。 |\n| **研发投入** | 研发费用极高（推测2022E超1180亿元），占收入比例约17%，属典型技术驱动型企业。 |\n| **税收优势** | 实际税率约10%，享受显著税收优惠，提升净利润水平。 |\n| **财务健康** | 财务费用低，EBITDA增长快，偿债与运营能力较强。 |\n\n---\n\n### 四、潜在问题与注意事项\n\n1. **研发费用数据异常**：  \n   - 2021E单元格包含四个数值，明显是格式错误。应核实正确数值分布（可能为2021E–2024E的预测）。若2021E为969亿，则合理；若更高，则需评估其可持续性。\n\n2. **2019年业绩下滑原因**：  \n   - 营业利润下降40%，需结合外部环境（如行业调整、政策变化、一次性支出）进一步分析。\n\n3. **高销售费用**：  \n   - 销售费用占比近27%，若不能持续转化为收入增长，可能存在效率问题。\n\n4. **轻资产特征**：  \n   - 营业成本极低（仅占收入~12%），说明非制造业，可能是平台型、服务型或知识产权密集型企业（如互联网、AI、生物医药等）。\n\n---\n\n### 五、总结\n\n该利润表反映了一家**高成长、高研发投入、高毛利、轻资产模式**的企业，可能属于**高科技、生物医药、互联网或新能源**等行业。虽然2019年经历短期盈利下滑，但从2020年起进入高速成长通道，预计2022年营业收入接近6900亿元，归属母公司净利润达768亿元，EPS达0.68元，展现出强劲的发展势头和良好的盈利前景。\n\n投资者可重点关注其**研发成果转化能力、销售效率及税收优惠政策的可持续性**。",
        "metadata": {
            "filename": "公司研究广联达-造价业务转型加速推进施工业务整合效应初显-2020032615页.pdf",
            "page": 12,
            "type": "table",
            "img_path": "images/ee3a9567b30eb1dded7fd43ac00e7ced1e0e9b3e176daa5a8a694acb8fbc0e9f.jpg",
            "table_body": "<table><tr><td>至12月31日</td><td>2018A</td><td>2019A</td><td>2020E</td><td>2021E</td><td>2022E</td></tr><tr><td>营业收入</td><td>2,904</td><td>3,541</td><td>4,380</td><td>5,537</td><td>6,864</td></tr><tr><td>营业成本</td><td>188</td><td>371</td><td>496</td><td>667</td><td>864</td></tr><tr><td>营业税金及附加</td><td>45</td><td>43</td><td>53</td><td>67</td><td>83</td></tr><tr><td>销售费用</td><td>793</td><td>1,102</td><td>1,304</td><td>1,523</td><td>1,853</td></tr><tr><td>管理费用</td><td>765</td><td>820</td><td>985</td><td>1,218</td><td>1,476</td></tr><tr><td>研发费用</td><td>727.17</td><td></td><td></td><td>969.11 1182.52 1467.21 1784.53</td><td></td></tr><tr><td>财务费用</td><td>34.64</td><td>40.55</td><td>37.32</td><td>34.12</td><td>13.68</td></tr><tr><td>资产减值损失</td><td>55.81</td><td>-6.11</td><td>93.34</td><td>59.33</td><td>78.14</td></tr><tr><td>公允价值变动收益</td><td>0.00</td><td>0.00</td><td>0.00</td><td>0.00</td><td>0.00</td></tr><tr><td>投资净收益</td><td>21.99</td><td>22.51</td><td>21.00</td><td>20.50</td><td>20.80</td></tr><tr><td>营业利润</td><td>484.56</td><td>290.37</td><td>413.71</td><td>687.99</td><td>899.00</td></tr><tr><td>营业外收支</td><td>-2.94</td><td>-6.61</td><td>-2.20</td><td>-2.50</td><td>-2.20</td></tr><tr><td>利润总额</td><td>482</td><td>284</td><td>412</td><td>685</td><td>897</td></tr><tr><td>所得税</td><td>49</td><td>29</td><td>42</td><td>71</td><td>92</td></tr><tr><td>净利润</td><td>433</td><td>255</td><td>369</td><td>615</td><td>805</td></tr><tr><td>少数股东损益</td><td>-6</td><td>20</td><td>17</td><td>28</td><td>36</td></tr><tr><td>归属母公司净利润</td><td>439</td><td>235</td><td>353</td><td>587</td><td>768</td></tr><tr><td>EBITDA</td><td>459.74</td><td>341.36</td><td>472.37</td><td>722.94</td><td>948.02</td></tr><tr><td>EPS（元）</td><td>0.39</td><td>0.21</td><td>0.31</td><td>0.52</td><td>0.68</td></tr></table>"
        }
    },
    {
        "page_content": "这张表格的标题为“**现金流量表**”，单位为**百万元**，展示了某公司在不同年度的现金流量情况，涵盖**2018年（实际数据A）**、**2019年（实际数据A）**、以及**2020年至2022年的预测数据（E）**。表格从**经营活动、投资活动、筹资活动**三个维度详细拆解了现金流的构成，并提供了**现金净增加额、期初与期末现金余额**等关键财务指标。\n\n以下是表格内容的详细分析：\n\n---\n\n### 一、**经营活动现金流**\n\n经营活动现金流反映企业通过主营业务产生的现金流入和流出。\n\n- **2018年**：453 百万元  \n- **2019年**：641 百万元（同比增长约41.5%）  \n- **2020年（预测）**：740 百万元  \n- **2021年（预测）**：1,200 百万元（显著增长）  \n- **2022年（预测）**：1,360 百万元（持续增长）\n\n**构成分析：**\n\n1. **净利润**\n   - 2018年：433 百万元\n   - 2019年：255 百万元（同比下降约41%，盈利下滑）\n   - 2020年预测回升至369 百万元\n   - 2021年：615 百万元\n   - 2022年：805 百万元（恢复并持续增长）\n\n2. **折旧摊销**\n   - 持续增加：从2018年74 → 2022年145 百万元，体现固定资产投入或无形资产摊销增加。\n\n3. **营运资金变动**\n   - 2018年为负值（-133），表示营运资金占用现金；\n   - 2019年转正为216，说明营运效率改善；\n   - 2020–2022年保持正向贡献（150–405），尤其2021年达405，对现金流拉动明显。\n\n4. **其他**\n   - 波动较小，维持在60–107 百万元之间。\n\n> **总结**：尽管2019年净利润大幅下降，但因折旧摊销上升和营运资金改善，**经营现金流反而上升**；2020年后净利润回升，叠加营运资金优化，推动经营现金流在2021年跃升至1,200百万元以上。\n\n---\n\n### 二、**投资活动现金流**\n\n反映企业在资本支出、投资变动等方面的现金流动。\n\n- **2018年**：-18 百万元（小幅净流出）\n- **2019年**：-227 百万元（大幅流出）\n- **2020年**：-291 百万元（继续扩大流出）\n- **2021年**：-132 百万元（流出收窄）\n- **2022年**：-131 百万元（基本持平）\n\n**构成分析：**\n\n1. **资本支出（CapEx）**\n   - 持续为负：2018年-202 → 2019年-242 → 2020年-312（逐年扩大）\n   - 2021年降至-153，2022年-152，显示资本开支高峰已过。\n\n2. **投资变动**\n   - 2018年为+154（收回投资或出售资产）\n   - 2019年仅-17，2020–2022年为0，表明投资活动趋于稳定或暂停。\n\n3. **其他**\n   - 小额正流入，每年约21–32 百万元。\n\n> **总结**：公司在2018–2020年处于**大规模投资扩张期**，尤其是2020年资本支出高达312亿元；2021年起投资节奏放缓，投资活动现金流流出减少。\n\n---\n\n### 三、**筹资活动现金流**\n\n反映企业通过借款、股权融资等方式筹集资金的情况。\n\n- **2018年**：-82 百万元（净偿还）\n- **2019年**：-390 百万元（大幅净偿还）\n- **2020年**：-586 百万元（进一步净偿还）\n- **2021年**：-544 百万元（仍为净偿还）\n- **2022年**：0 百万元（停止筹资活动）\n\n**构成分析：**\n\n1. **银行借款**\n   - 2018年为+144（新增借款）\n   - 2019年起转为净偿还：-112 → -555（2020年）\n   - 2021年继续偿还-534\n   - 2022年为0，表明债务已清或不再变动\n\n2. **股权融资**\n   - 2018年为+106（可能为IPO或增发）\n   - 2019年仅+23，2020–2022年为0，说明再融资停止\n\n3. **其他**\n   - 2018年-332，2019年-301，为大额现金流出，可能涉及分红、担保或其他负债偿还；\n   - 2020年后大幅减少至-32以下，2022年为0。\n\n> **总结**：公司在2018年进行了一轮股权融资并新增借款，随后进入**持续还债阶段**，2019–2021年每年筹资现金流均为净流出超390亿元，至2022年**完全停止筹资活动**，财务趋于保守。\n\n---\n\n### 四、**现金净增加额**\n\n即三类活动现金流之和，反映年度现金总量变化。\n\n- **2018年**：+353 百万元（大幅增加）\n- **2019年**：+24 百万元（几乎持平）\n- **2020年**：-137 百万元（现金减少）\n- **2021年**：+523 百万元（强劲回流）\n- **2022年**：+1,229 百万元（历史最高）\n\n> **趋势解读**：\n- 2018年现金流大幅增长；\n- 2019年因投资与还债，增长微弱；\n- 2020年现金净减少，压力较大；\n- 2021年起经营现金流大幅改善，投资支出下降，带动现金强劲回流；\n- **2022年现金净增加近123亿元**，财务状况显著好转。\n\n---\n\n### 五、**现金余额变化**\n\n- **期初现金余额**：\n  - 2018年：1,837 百万元\n  - 逐年变化，2022年为2,617 百万元\n\n- **期末现金余额**：\n  - 2018年：2,210 百万元\n  - 2019年：2,230 百万元（基本持平）\n  - 2020年：2,094 百万元（下降）\n  - 2021年：2,617 百万元（回升）\n  - **2022年：3,846 百万元**（大幅增长）\n\n> **趋势**：现金余额在2020年触底后，2021–2022年快速回升，**两年累计增加约1,750百万元（17.5亿元）**，显示企业流动性显著增强。\n\n---\n\n### 综合分析与结论：\n\n1. **财务转型路径清晰**：\n   - **2018–2019年**：扩张与调整期 —— 投资加大、盈利下滑、偿还债务。\n   - **2020年**：压力期 —— 净利润恢复但筹资与投资双重流出，现金净减少。\n   - **2021–2022年**：收获期 —— 经营现金流爆发式增长，投资放缓，停止还债，现金大幅积累。\n\n2. **经营质量提升**：\n   - 虽然2019年净利润下降，但后续恢复迅速；\n   - 营运资金管理改善，成为经营现金流增长的重要驱动力。\n\n3. **资本开支周期见顶**：\n   - 2020年为投资高峰，之后资本支出回落，企业由“投入期”转向“产出期”。\n\n4. **财务杠杆下降**：\n   - 连续多年偿还银行借款，2022年无新增融资，财务风险降低。\n\n5. **未来现金流前景乐观**：\n   - 2022年期末现金达**384.6亿元**，为历史最高水平；\n   - 若经营持续向好，公司具备较强抗风险能力和投资/分红潜力。\n\n---\n\n### 总结一句话：\n> 该企业经历了2018–2020年的**高投入、高偿还、低增长**阶段，自2021年起进入**经营改善、现金回流、财务修复**的新周期，2022年现金流状况达到历史最佳水平。",
        "metadata": {
            "filename": "公司研究广联达-造价业务转型加速推进施工业务整合效应初显-2020032615页.pdf",
            "page": 12,
            "type": "table",
            "img_path": "images/c75dfbabab0446679819ae8b0f5d0bf6cacebcf36daf49d514838f130ed621db.jpg",
            "table_body": "<table><tr><td>至12月31日</td><td>2018A 2019A</td><td>2020E</td><td></td><td>2021E</td><td>2022E</td></tr><tr><td>经营活动现金流</td><td>453</td><td>641</td><td>740</td><td>1,200</td><td>1,360</td></tr><tr><td>净利润</td><td>433</td><td>255</td><td>369</td><td>615</td><td>805</td></tr><tr><td>折旧摊销</td><td>74</td><td>106</td><td>114</td><td>128</td><td>145</td></tr><tr><td>营运资金变动</td><td>-133</td><td>216</td><td>150</td><td>405</td><td>351</td></tr><tr><td>其它</td><td>79</td><td>65</td><td>107</td><td>52</td><td>60</td></tr><tr><td>投资活动现金流</td><td>-18</td><td>-227</td><td>-291</td><td>-132</td><td>-131</td></tr><tr><td>资本支出</td><td>-202</td><td>-242</td><td>-312</td><td>-153</td><td>-152</td></tr><tr><td>投资变动</td><td>154</td><td>-17</td><td>0</td><td>0</td><td>0</td></tr><tr><td>其他</td><td>31</td><td>32</td><td>21</td><td>21</td><td>21</td></tr><tr><td>筹资活动现金流</td><td>-82</td><td>-390</td><td>-586</td><td>-544</td><td>0</td></tr><tr><td>银行借款</td><td>144</td><td>-112</td><td>-555</td><td>-534</td><td>0</td></tr><tr><td>股权融资</td><td>106</td><td>23</td><td>0</td><td>0</td><td>0</td></tr><tr><td>其他</td><td>-332</td><td>-301</td><td>-32</td><td>-11</td><td>0</td></tr><tr><td>现金净增加额</td><td>353</td><td>24</td><td>-137</td><td>523</td><td>1,229</td></tr><tr><td>期初现金余额</td><td>1,837</td><td>2,210</td><td>2,231</td><td>2,094</td><td>2,617</td></tr><tr><td>期末现金余额</td><td>2,210</td><td>2,230</td><td>2,094</td><td>2,617</td><td>3,846</td></tr></table>"
        }
    },
    {
        "page_content": "该表格标题为 **“主要财务比率”**，涵盖了某公司从 **2018年到2022年**（其中2018A和2019A为实际数据，2020E、2021E、2022E为预测数据）的多项关键财务指标，按不同维度分为五大类：**成长能力、获利能力、偿债能力、营运能力、每股指标与估值比率**。以下是对表格内容的详细分析和描述：\n\n---\n\n### 一、成长能力\n\n反映公司收入和利润的增长趋势。\n\n| 指标 | 2018A | 2019A | 2020E | 2021E | 2022E |\n|------|------|------|------|------|------|\n| 营业收入增长 | 23.2% | 21.9% | 23.7% | 26.4% | 24.0% |\n| 营业利润增长 | -5.8% | -40.1% | 42.5% | 66.3% | 30.7% |\n| 归母净利润增长 | -7.0% | -46.5% | 50.0% | 66.6% | 30.8% |\n\n- **营业收入**保持稳定高增长，2018–2022年均在20%以上，2021年预计达到峰值26.4%，显示公司主营业务持续扩张。\n- **营业利润与归母净利润**在2018–2019年出现显著下滑，分别下降5.8%和7.0%（2018），2019年更是大幅下滑至-40.1%和-46.5%，表明期间盈利能力遭遇严重压力（可能受成本上升或一次性支出影响）。\n- 但从2020年起，盈利增速强劲反弹，预计2020–2021年归母净利润增速分别达50%和66.6%，2022年回落至30.8%，仍维持高增长，反映公司盈利修复趋势明显。\n\n---\n\n### 二、获利能力\n\n衡量公司盈利质量和资本回报水平。\n\n| 指标 | 2018A | 2019A | 2020E | 2021E | 2022E |\n|------|------|------|------|------|------|\n| 毛利率 | 93.5% | 89.5% | 88.7% | 88.0% | 87.4% |\n| 净利率 | 14.9% | 7.2% | 8.4% | 11.1% | 11.7% |\n| ROE（净资产收益率） | 13.8% | 7.2% | 9.7% | 14.0% | 15.4% |\n| ROIC（投入资本回报率） | 17.2% | 9.6% | 14.8% | 30.7% | 54.5% |\n\n- **毛利率**极高，始终保持在87%以上，2018年高达93.5%，即使逐年小幅下降，也说明公司产品或服务具有极强的定价能力和成本控制优势（如软件、医药、高端消费等行业特征）。\n- **净利率**在2019年大幅下滑至7.2%，但随后回升，2022年预计达11.7%，接近2018年水平。\n- **ROE**从2018年的13.8%降至2019年7.2%，2020年起回升，2022年预计达15.4%，显示股东回报能力逐步恢复并增强。\n- **ROIC**表现尤为亮眼：从2019年9.6%快速上升至2021年30.7%、2022年54.5%，翻数倍，表明公司资本使用效率大幅提升，投资回报极高，可能是业务扩张见效或轻资产运营模式优化所致。\n\n---\n\n### 三、偿债能力\n\n评估公司债务风险和短期偿付能力。\n\n| 指标 | 2018A | 2019A | 2020E | 2021E | 2022E |\n|------|------|------|------|------|------|\n| 资产负债率 | 41.5% | 45.7% | 44.0% | 41.1% | 41.5% |\n| 净负债比率 | 21.3% | 17.7% | 8.0% | 0.0% | 0.0% |\n| 流动比率 | 2.08 | 1.05 | 1.12 | 1.32 | 1.49 |\n| 速动比率 | 2.05 | 1.03 | 1.10 | 1.29 | 1.46 |\n\n- **资产负债率**在41%-46%之间波动，2019年最高（45.7%），之后略有下降，处于合理区间，表明公司杠杆适中，财务结构较稳健。\n- **净负债比率**从21.3%持续下降至2021–2022年的0%，意味着公司现金足以覆盖有息负债，甚至无净负债，财务安全性极高。\n- **流动比率与速动比率**在2018年很高（>2），但2019年骤降至1.05和1.03，短期偿债能力承压；不过从2020年起稳步回升，2022年达1.49和1.46，流动性压力缓解，短期偿债能力改善。\n\n---\n\n### 四、营运能力\n\n反映公司资产运营效率。\n\n| 指标 | 2018A | 2019A | 2020E | 2021E | 2022E |\n|------|------|------|------|------|------|\n| 总资产周转率 | 0.55 | 0.60 | 0.68 | 0.79 | 0.85 |\n| 应收账款周转率 | 13.82 | 7.96 | 7.96 | 7.96 | 7.96 |\n| 存货周转率 | 19.58 | 24.22 | 24.22 | 24.22 | 24.22 |\n\n- **总资产周转率**逐年提升，从0.55升至2022年0.85，说明公司利用资产创造收入的能力不断增强，运营效率显著提高。\n- **应收账款周转率**在2018年为13.82，2019年起稳定在7.96，虽有所下降，但保持稳定，年均约每45天回款一次（365÷7.96≈45.8天），回款速度尚可。\n- **存货周转率**从2018年19.58提升至2019年24.22，并保持不变，说明库存管理效率提升，存货变现速度快。\n\n---\n\n### 五、每股指标（元）\n\n体现股东层面的价值创造。\n\n| 指标 | 2018A | 2019A | 2020E | 2021E | 2022E |\n|------|------|------|------|------|------|\n| 每股收益（EPS） | 0.39 | 0.21 | 0.31 | 0.52 | 0.68 |\n| 每股经营现金流 | 0.40 | 0.57 | 0.66 | 1.06 | 1.21 |\n| 每股净资产 | 2.83 | 2.90 | 3.21 | 3.73 | 4.41 |\n\n- **EPS**在2019年降至0.21元，2020年起快速回升，2022年达0.68元，盈利能力恢复且超越前期水平。\n- **每股经营现金流**始终高于EPS，尤其在2021–2022年大幅增长至1.06元和1.21元，说明盈利质量高，现金生成能力强。\n- **每股净资产**持续增长，从2.83元增至4.41元，反映公司净资产积累加快，股东权益稳步提升。\n\n---\n\n### 六、估值比率\n\n用于衡量市场对公司价值的评估。\n\n| 指标 | 2018A | 2019A | 2020E | 2021E | 2022E |\n|------|------|------|------|------|------|\n| P/E（市盈率） | 53.39 | 163.13 | 135.27 | 81.20 | 62.07 |\n| P/B（市净率） | 7.34 | 11.73 | 13.16 | 11.33 | 9.58 |\n| EV/EBITDA（企业价值倍数） | 48.77 | 108.99 | 97.66 | 62.35 | 46.25 |\n\n- **P/E**在2019年高达163倍，估值极高，可能因当年利润基数低（EPS仅0.21元）所致；随后随利润增长迅速回落，2022年降至62倍，估值趋于合理。\n- **P/B**从2018年7.34倍上升至2020年13.16倍，之后回落至9.58倍，仍处于较高水平，反映市场对公司资产质量或成长性的溢价认可。\n- **EV/EBITDA**走势与P/E类似，2019年超108倍，2022年降至46倍，显示企业整体估值在逐步回归理性。\n\n---\n\n### 综合分析与趋势判断：\n\n1. **成长性强劲**：尽管2019年利润短暂承压，但自2020年起收入与利润双双高增长，尤其是净利润增速连续两年超50%，成长动力充足。\n\n2. **盈利能力卓越**：超高毛利率（>87%）+ ROIC飙升至54.5%，表明公司具备极强的竞争壁垒和资本回报能力。\n\n3. **财务结构稳健**：资产负债率适中，净负债率归零，流动性逐年改善，偿债风险极低。\n\n4. **运营效率提升**：总资产周转率持续上升，资产利用效率提高；存货和应收账款管理稳定高效。\n\n5. **股东回报增强**：EPS、每股现金流、每股净资产全面增长，股东价值不断提升。\n\n6. **估值逐步回归合理**：前期因盈利下滑导致估值虚高（P/E >160），但随着盈利恢复，P/E和EV/EBITDA显著下降，投资吸引力增强。\n\n---\n\n### 结论：\n\n该企业是一家**高毛利、高成长、高资本回报**的优质公司，经历2019年的短期盈利低谷后，自2020年起全面复苏，财务状况持续改善，运营效率提升，估值趋于合理。未来若能维持当前增长势头，具备较强的长期投资价值。",
        "metadata": {
            "filename": "公司研究广联达-造价业务转型加速推进施工业务整合效应初显-2020032615页.pdf",
            "page": 12,
            "type": "table",
            "img_path": "images/9129d7519fd1748a21117a3b273ac8a54546238f05de6e89c52026d08eb5d95e.jpg",
            "table_body": "<table><tr><td>至12月31日</td><td>2018A</td><td>2019A</td><td>2020E</td><td>2021E</td><td>2022E</td></tr><tr><td>成长能力</td><td></td><td></td><td></td><td></td><td></td></tr><tr><td>营业收入增长</td><td>23.2%</td><td>21.9%</td><td>23.7%</td><td>26.4%</td><td>24.0%</td></tr><tr><td>营业利润增长</td><td>-5.8%</td><td>-40.1%</td><td>42.5%</td><td>66.3%</td><td>30.7%</td></tr><tr><td>归母净利润增长</td><td>-7.0%</td><td>-46.5%</td><td>50.0%</td><td>66.6%</td><td>30.8%</td></tr><tr><td>获利能力</td><td></td><td></td><td></td><td></td><td></td></tr><tr><td>毛利率</td><td>93.5%</td><td>89.5%</td><td>88.7%</td><td>88.0%</td><td>87.4%</td></tr><tr><td>净利率</td><td>14.9%</td><td>7.2%</td><td>8.4%</td><td>11.1%</td><td>11.7%</td></tr><tr><td>ROE</td><td>13.8%</td><td>7.2%</td><td>9.7%</td><td>14.0%</td><td>15.4%</td></tr><tr><td>ROIC</td><td>17.2%</td><td>9.6%</td><td>14.8%</td><td>30.7%</td><td>54.5%</td></tr><tr><td>偿债能力</td><td></td><td></td><td></td><td></td><td></td></tr><tr><td>资产负债率</td><td>41.5%</td><td>45.7%</td><td>44.0%</td><td>41.1%</td><td>41.5%</td></tr><tr><td>净负债比率</td><td>21.3%</td><td>17.7%</td><td>8.0%</td><td>0.0%</td><td>0.0%</td></tr><tr><td>流动比率</td><td>2.08</td><td>1.05</td><td>1.12</td><td>1.32</td><td>1.49</td></tr><tr><td>速动比率</td><td>2.05</td><td>1.03</td><td>1.10</td><td>1.29</td><td>1.46</td></tr><tr><td>营运能力</td><td></td><td></td><td></td><td></td><td></td></tr><tr><td>总资产周转率</td><td>0.55</td><td>0.60</td><td>0.68</td><td>0.79</td><td>0.85</td></tr><tr><td>应收账款周转率</td><td>13.82</td><td>7.96</td><td>7.96</td><td>7.96</td><td>7.96</td></tr><tr><td>存货周转率</td><td>19.58</td><td>24.22</td><td>24.22</td><td>24.22</td><td>24.22</td></tr><tr><td>每股指标（元）</td><td></td><td></td><td></td><td></td><td></td></tr><tr><td>每股收益</td><td>0.39</td><td>0.21</td><td>0.31</td><td>0.52</td><td>0.68</td></tr><tr><td>每股经营现金流</td><td>0.40</td><td>0.57</td><td>0.66</td><td>1.06</td><td>1.21</td></tr><tr><td>每股净资产</td><td>2.83</td><td>2.90</td><td>3.21</td><td>3.73</td><td>4.41</td></tr><tr><td>估值比率</td><td></td><td></td><td></td><td></td><td></td></tr><tr><td>P/E</td><td>53.39</td><td>163.13</td><td>135.27</td><td>81.20</td><td>62.07</td></tr><tr><td>P/B</td><td>7.34</td><td>11.73</td><td>13.16</td><td>11.33</td><td>9.58</td></tr><tr><td>EV/EBITDA</td><td>48.77</td><td>108.99</td><td>97.66</td><td>62.35</td><td>46.25</td></tr></table>"
        }
    },
    {
        "page_content": "",
        "metadata": {
            "filename": "公司研究广联达-造价业务转型加速推进施工业务整合效应初显-2020032615页.pdf",
            "page": 12,
            "type": "text",
            "img_path": "None",
            "table_body": "None"
        }
    }
]