[
    {
        "page_content": "这张图片的标题为“图24：连连全球支付牌照/资质及驻点”，是一张以深蓝色为背景的世界地图，展示了连连（LianLian）在全球范围内的支付牌照、资质以及业务驻点分布情况。\n\n### 图像整体布局：\n- 地图采用简洁的线条勾勒出各大洲轮廓，包括亚洲、欧洲、非洲、北美洲、南美洲、大洋洲和部分北极区域。\n- 地图上使用了两种不同样式的图标来标记两类信息：\n  - **蓝色圆形图标**：代表“全球牌照及资质”；\n  - **黄色方形图标**：代表“全球驻点”。\n\n---\n\n### 各地区详细标注：\n\n#### 1. **中国（CHINA）**\n- 位于地图中央偏左位置，是中国大陆及其周边国家的中心区域。\n- 在中国大陆及周边地区（如香港、台湾等）有多个蓝色圆形图标，表示在这些地区拥有支付相关的牌照或资质。\n- 部分城市如上海、北京、深圳等地可能设有驻点，但未明确标出具体名称。\n\n#### 2. **东南亚地区**\n- **新加坡（SINGAPORE）**：有黄色方形图标（驻点）和蓝色圆形图标（牌照/资质），显示在此地设有运营机构并具备相关合规资质。\n- **泰国（THAILAND）**：有黄色方形图标，表明设有驻点。\n- **印度尼西亚（INDONESIA）**：有黄色方形图标，显示存在业务驻点。\n- **马来西亚（MALAYSIA）、越南（VIETNAM）等国**：也有少量黄色方形图标，表示设有驻点。\n\n#### 3. **欧洲**\n- **英国（UNITED KINGDOM）**：有蓝色圆形图标（牌照/资质）和黄色方形图标（驻点），说明在英国既有合规资质，也设有本地团队或办事处。\n- **欧洲其他地区**：如德国、法国、荷兰等国家虽未直接命名，但在欧洲大陆上有多个蓝色圆形图标，表明连连在欧洲多国获得了支付相关的监管许可。\n\n#### 4. **北美**\n- **美国（UNITED STATES）**：有大量蓝色圆形图标，集中在东部沿海城市（如纽约、旧金山）及西部地区，显示其在美国多地拥有支付牌照或资质。\n- **加拿大（CANADA）**：有蓝色圆形图标，表明已获得当地支付相关资质。\n- 美国境内还有多个黄色方形图标，代表在主要城市设有驻点。\n\n#### 5. **南美**\n- **巴西（BRAZIL）**：有一个黄色方形图标，表示设有驻点，是连连在南美的重要布局点。\n\n#### 6. **大洋洲**\n- **澳大利亚（AUSTRALIA）**：有蓝色圆形图标（牌照/资质）和黄色方形图标（驻点），说明在澳拥有合法运营资格，并设有本地团队。\n\n#### 7. **中东与非洲**\n- **中东（MIDDLE EAST）**：有蓝色圆形图标，表明在该区域取得了某些支付牌照或资质，但未见明显驻点标识。\n- **非洲（AFRICA）**：目前无明显图标，表明暂无公开的牌照或驻点布局。\n\n---\n\n### 图例说明：\n- **蓝色圆点**：全球牌照及资质 —— 表示连连在当地已获得合法的支付业务许可或金融监管批准。\n- **黄色方块**：全球驻点 —— 表示连连在当地设有实体办公地点或服务团队，用于支持本地化运营和服务。\n\n---\n\n### 总结：\n这张图清晰展现了连连科技在全球范围内的合规布局和业务网络。其核心优势在于：\n- 在**中国、美国、欧洲、东南亚、澳大利亚、巴西**等多个主要市场均具备支付牌照或资质；\n- 在关键市场如美国、英国、新加坡、澳大利亚、巴西等地设有**本地驻点**，便于提供本地化服务；\n- 布局覆盖了全球主要经济区域，显示出较强的国际化能力和全球服务能力。\n\n该图可用于展示连连在全球支付领域的合规性、扩展能力以及国际业务影响力。",
        "metadata": {
            "filename": "连连数字-港股公司研究报告-全球化牌照与稳定币创新双轮驱动跨境支付巨头迎盈利拐点-25071428页.pdf",
            "page": 18,
            "type": "image",
            "img_path": "images/8521ffaef7a40d6fb4522dc534cc9e02e013b4c410884e50c430f59ef8f14842.jpg",
            "table_body": "None"
        }
    },
    {
        "page_content": "这张图片的标题为“图25：2020-2024 年连连数字增值服务业务营收及 yoy”，是一张结合了柱状图和折线图的复合图表，用于展示连连数字在2020年至2024年期间增值服务业务的营业收入及其同比增长率（yoy）。\n\n### 图表构成：\n- **横轴（X轴）**：表示年份，从2020年到2024年。\n- **左纵轴（Y轴，左侧）**：表示增值服务营收，单位为百万元人民币（即百万元），数值范围从0到160。\n- **右纵轴（Y轴，右侧）**：表示同比增长率（yoy），单位为百分比（%），数值范围从0%到350%。\n- **深蓝色柱状图**：代表每年的增值服务营收（以百万元计）。\n- **浅灰色折线图**：代表每年的同比增长率（yoy）。\n\n---\n\n### 数据详情：\n\n#### 1. 增值服务营收（百万元）：\n- **2020年**：7.8 百万元（即780万元）\n- **2021年**：21.81 百万元（即2181万元）\n- **2022年**：91.05 百万元（即9105万元）\n- **2023年**：133.54 百万元（即1.3354亿元）\n- **2024年**：146.19 百万元（即1.4619亿元）\n\n#### 2. 同比增长率（yoy）：\n- **2021年**：180%（相对于2020年增长180%）\n- **2022年**：317%（相对于2021年增长317%）\n- **2023年**：47%（相对于2022年增长47%）\n- **2024年**：9%（相对于2023年增长9%）\n\n> 注：2020年无同比数据，因此没有标注yoy。\n\n---\n\n### 趋势分析：\n- **营收增长趋势**：从2020年的7.8百万元稳步上升至2024年的146.19百万元，整体呈现显著增长态势。其中，2021年和2022年增长尤为迅猛。\n- **增速变化**：同比增长率在2022年达到峰值317%，之后开始明显放缓，2023年降至47%，2024年进一步下降至9%，表明增速趋于平缓，进入成熟期或市场饱和阶段。\n\n---\n\n### 总结：\n该图表清晰地展示了连连数字增值服务业务在过去五年中实现了快速扩张，尤其在2021至2022年间爆发式增长。然而，随着基数增大，后续年度的同比增长率逐步回落，反映出业务增长模式可能正在从高增长向稳定发展过渡。",
        "metadata": {
            "filename": "连连数字-港股公司研究报告-全球化牌照与稳定币创新双轮驱动跨境支付巨头迎盈利拐点-25071428页.pdf",
            "page": 18,
            "type": "image",
            "img_path": "images/cf4377faee6975fb2de0bbabc3758b6dbf8ff6e67e94799687a7be574629827f.jpg",
            "table_body": "None"
        }
    },
    {
        "page_content": "# （三） 增值服务\n连连增值服务包括商业服务与技术服务。其中商业服务包括数字化营销、运营支持（例如在电商平台开设店铺及安排发货）及引流服务；技术服务包括账户及电子钱包服务以及软件开发服务。\n作为公司数字支付业务的衍生业务，近年来增值业务从小基数实现了高增长。2020-2024 年间，增值业务营收从 780 万元增长至 1.46 亿元，CAGR 为 $1 0 8 . 0 7 \\%$ ，2024 年同比增长率为 $+ 9 . 4 7 \\%$ ，增长主要来自于数字化营销服务的进一步拓展和虚拟银行卡业务的收入增长。\n",
        "metadata": {
            "filename": "连连数字-港股公司研究报告-全球化牌照与稳定币创新双轮驱动跨境支付巨头迎盈利拐点-25071428页.pdf",
            "page": 18,
            "type": "text",
            "img_path": "None",
            "table_body": "None"
        }
    }
]