[
    {
        "page_content": "这张图片的标题为“图表1：千味央厨品牌历程”，是一张以时间轴形式呈现的公司发展历程图，展示了千味央厨自2002年成立以来的关键发展节点和重要里程碑。整体采用横向时间轴结构，从左至右按年份顺序排列，每个关键年份对应一个或多个事件框，通过蓝色线条连接，清晰地展现了企业的发展脉络。\n\n以下是该图的详细内容描述：\n\n---\n\n### **时间轴主干**\n- 时间轴从**2002年**开始，延伸至**2021年**，以灰色圆点标注每一年。\n- 蓝色实线代表主要发展路径，虚线连接各个事件框与对应的年份。\n\n---\n\n### **各年度关键事件**\n\n#### **2002年**\n- **安心油条诞生**  \n  标志着千味央厨早期产品的推出，是其进入中式传统食品领域的起点。\n\n#### **2006年**\n- **开创中式传统产品进入西式餐饮全球销售网络**  \n  表明公司实现了中餐产品在国际连锁餐饮体系中的应用，具有战略意义。\n\n#### **2012年**\n- **步入快速发展阶段**\n- **新生产车间投产，提升大B服务能力**\n- **上海研发中心成立**  \n  显示公司在产能、服务能力和研发能力上的全面提升。\n\n#### **2013年**\n- **千味央厨成立**\n- **开创专业餐饮B2B道路**\n- **成立之初明星单品芝麻球销售额超国内80%以上速冻企业总销售额**  \n  强调公司成立初期即取得显著市场表现，尤其在明星单品上具备突出竞争力。\n\n#### **2014年**\n- **实现餐饮定制化专业服务**  \n  表明公司开始向客户提供个性化、定制化的解决方案，增强客户粘性。\n\n#### **2015年**\n- **全面升级走向国际**\n- **进入百胜T1级别供应商**\n- **通过麦当劳国际业务审核**\n- **与泰国麦当劳建立合作**  \n  这些事件标志着千味央厨成功打入国际知名快餐巨头供应链，具备全球化运营能力。\n\n#### **2016年**\n- **精细管理启动上市**\n- **通过FSSC22000国际食品体系、HACCP体系、ISO22000食品安全体系、ISO9001质量体系认证**\n- **荣获百胜餐饮集团中国事业部“供应管理奖”称号**\n- **开创全物流成品仓储托管**  \n  反映公司在管理体系、品质控制和物流服务方面达到行业领先水平。\n\n#### **2017年**\n- **新乡一期正式投产**\n- **京东领投千味央厨**\n- **锐变：全新领导班子**\n- **12月23日新乡平原一期工厂开工**  \n  展示了公司在生产扩张、资本运作和组织架构方面的重大调整。\n\n#### **2018年**\n- **千味央厨新乡市平原示范区新厂建设启动**  \n  表明公司持续扩大产能布局，强化生产基地建设。\n\n#### **2019年**\n- **6月新乡生产基地通过BRC A级认证**  \n  BRC（英国零售商协会）A级认证是国际公认的高标准食品安全认证，体现其产品质量达到国际一流水平。\n\n#### **2021年**\n- **9月6日：上市**\n- **荣获政府认证“种子独角兽企业”**  \n  标志着千味央厨完成资本市场登陆，并获得政府对高成长性企业的认可。\n\n---\n\n### **整体特点**\n- 图表结构清晰，信息层级分明，使用蓝色边框矩形表示事件，白色背景搭配黑色文字，视觉简洁易读。\n- 每个事件前均用“✓”符号标注，强调达成的重要成就。\n- 时间轴设计合理，重点突出企业发展过程中的关键转折点，如产品创新、市场拓展、资质认证、资本运作和上市等。\n\n---\n\n### **总结**\n该图全面系统地回顾了千味央厨从初创到上市的成长历程，突出了其在产品研发、市场开拓、质量管理、国际化布局和资本化进程中的核心进展，充分体现了其作为中国领先的餐饮B2B食材供应商的综合实力和发展轨迹。",
        "metadata": {
            "filename": "千味央厨-稳定成长兼具千味奋进正当时-22051927页.pdf",
            "page": 4,
            "type": "image",
            "img_path": "images/296d5b0d33a8051c619ca8deab342157492437a33e3c1cfb2de9d68bdee0dc90.jpg",
            "table_body": "None"
        }
    },
    {
        "page_content": "# 1. 出身于思念的“餐饮供应链第一股”\n# 1.1.出身思念系，专注餐饮供应解决方案\n公司为思念系出身，多年来精耕 B 端渠道速冻米面制品供应。千味央廚于 2012 年 4 月由郑州思念出资成立，秉承“只为餐饮·厨师之选”的战略定位，致力于为餐饮、酒店、团餐提供全面供应解决方案，作为国内知名的B端速冻米面供应商，公司已与肯德基、必胜客、海底捞、华莱士、真功夫、九毛九、呷哺呷哺等多个知名餐饮品牌达成深度战略合作，系百胜中国T1级供应商。公司发展共分为三个阶段：\n1）起步积累期：2002-2012 年。百胜餐饮与孕育在思念体系下的千味央厨合作，从蛋挞到“安心油条\"，开创了中式传统产品进入西式连锁餐饮的先河。\n2）快速成立期：2012-2016 年。公司开创专业餐饮 B2B 道路，成立郑州、上海两大研发基地，实现定制化专业服务。\n3)独立发展期：2016 年至今。2016 年 3 月思念将所持千味股权 $100 \\%$ 转让给郑州集之城，千味脱离思念系，公司品牌升级转型，开始独立高速发展。\n业绩稳健增长，具备成长性。2021年公司实现营收12.7亿元，同比 $+ 3 4 . 9 \\%$ ；归母净利0.9亿元，同比 $+ 1 5 . 5 \\%$ 。整体来看，2017-2021年营收及归母净利润的CAGR 分别为 $+ 2 1 . 1 \\% / + 1 7 . 4 \\%$ ，维持良好增长态势。\n构建“一超多强”产品矩阵，打造中华特色大单品。经过多年品类拓展，公司已经形成了包含油炸类、烘焙类、蒸煮类、菜肴类及其他在内的四大类产品体系，并持续发力打造各品类下的大单品。1）从收入来看：2021 年油炸/烘焙/蒸煮/菜肴类产品营收分别为 $6 . 6 / 2 . 2 / 2 . 6 / 1 . 3$ 亿元，分别同比 $+ 2 6 . 7 \\% / + 1 9 . 1 \\% / + 3 9 . 2 \\% / + 1 6 2 . 1 \\%$ ，SKU数达300 余种。其中，核心大单品增速显著：油条类产品贡献营收3.5 亿元，同比 $+ 3 4 . 7 \\%$ （除百胜外同比 $+ 4 3 . 9 \\%$ )，主要系经销商渠道放量；蒸煎饺营收1.4亿元，同比$+ 1 6 7 . 9 \\%$ ，主要系公司加大研发及推广力度；面点产品营收1.2 亿，同比增长近 $30 \\%$ 主要系卡通包放量；此外公司预制菜销售超1400多万，同比 $+ 3 4 . 4 \\%$ ；2）毛利率角度看：蒸煮、烘焙类产品毛利率较高，2021 年分别为 $2 3 . 5 \\% / 2 5 . 0 \\%$ ；油炸类产品毛利率相对较低，较其他高毛利品类低约3-4pct，近年来营收占比有所下降，促进整体毛利\n",
        "metadata": {
            "filename": "千味央厨-稳定成长兼具千味奋进正当时-22051927页.pdf",
            "page": 4,
            "type": "text",
            "img_path": "None",
            "table_body": "None"
        }
    }
]