[
    {
        "page_content": "标题为“图55 2020 年各项业务收入占比”的这张图片是一张饼状图，用于展示某公司在2020年不同业务板块的收入构成比例。图表通过不同颜色的扇形区域表示各业务板块的收入占比，并在图例中对应标注了具体业务类别。\n\n具体内容如下：\n\n- **建筑、工程和施工（AEC）**：占比最大，为 **43%**，用橙色表示，是公司收入的主要来源。\n- **制造（MFG）**：占比为 **29%**，用深红色表示，是第二大收入来源。\n- **AutoCAD 和 AutoCAD LT**：占比为 **21%**，用黄色表示，属于软件产品相关业务。\n- **传媒娱乐（M&E）**：占比为 **6%**，用浅绿色表示。\n- **其他**：占比最小，为 **1%**，用浅灰色表示，涵盖未单独列示的其他业务。\n\n该饼图清晰地反映了该公司在2020年的收入结构，其中 AEC 业务占据主导地位，其次是制造和 AutoCAD 软件产品，传媒娱乐和其他业务占比较小。整体来看，公司的收入主要集中在建筑、工程与施工以及制造业领域。",
        "metadata": {
            "filename": "广联达-公司深度报告开启新增长极-22022246页.pdf",
            "page": 42,
            "type": "image",
            "img_path": "images/e3eb4b5e465873e1ab4228e7b3791cf95b8260719901378b1152189b4677311f.jpg",
            "table_body": "None"
        }
    },
    {
        "page_content": "这张图片是一张柱状图，标题为“图56 2018-2020年订阅收入及维护收入”，展示了某公司在2017年至2020年期间的**订阅收入**和**维护收入**的变化情况。图表以百万美元为单位，横轴表示年份（2017–2020），纵轴表示收入金额（单位：百万美元），数值范围从0到4,000。\n\n### 图表内容详细描述：\n\n#### 1. **数据分类**\n- 橙色柱子代表 **订阅收入**（Subscription Revenue）\n- 红色柱子代表 **维护收入**（Maintenance Revenue）\n\n#### 2. **各年份具体数据**\n\n| 年份 | 订阅收入（百万美元） | 维护收入（百万美元） |\n|------|------------------------|------------------------|\n| 2017 | 894.3                  | 989.6                  |\n| 2018 | 1802.3                 | 635.1                  |\n| 2019 | 2751.9                 | 386.6                  |\n| 2020 | 3478.9                 | 183.3                  |\n\n#### 3. **趋势分析**\n\n- **订阅收入**：\n  - 从2017年的894.3百万美元持续快速增长。\n  - 2018年增长至1802.3百万美元（约翻倍）。\n  - 2019年进一步增至2751.9百万美元。\n  - 2020年达到最高点3478.9百万美元，显示出强劲的增长势头。\n\n- **维护收入**：\n  - 从2017年的989.6百万美元开始逐年下降。\n  - 2018年降至635.1百万美元。\n  - 2019年继续下滑至386.6百万美元。\n  - 2020年进一步减少至183.3百万美元，呈现显著萎缩趋势。\n\n#### 4. **对比与结论**\n- 在整个时间段内，**订阅收入持续大幅增长**，而**维护收入则持续下降**。\n- 这表明该公司可能正在从传统的“一次性销售+后期维护”模式向“订阅制服务”转型，客户更倾向于长期订阅服务而非一次性购买加维护。\n- 到2020年，订阅收入已远超维护收入，成为公司主要收入来源。\n\n#### 5. **视觉特征**\n- 图表使用清晰的颜色区分两种收入类型（橙色 vs 红色）。\n- 每根柱子上方标注了具体的数值，便于读取。\n- 坐标轴有明确刻度，易于比较不同年份的数据。\n\n### 总结：\n该图表直观地反映了该公司在2017–2020年间业务模式的转变：**订阅收入迅速扩张，而传统维护收入不断萎缩**，说明其商业模式正朝着可持续、可预测的订阅经济方向发展。",
        "metadata": {
            "filename": "广联达-公司深度报告开启新增长极-22022246页.pdf",
            "page": 42,
            "type": "image",
            "img_path": "images/ae6ed0fcf8145377667613176b3966c2c77748f9c679024811083145c04d167c.jpg",
            "table_body": "None"
        }
    },
    {
        "page_content": "标题为“图57：2018-2020年递延收入及其增速”的图表是一张结合了柱状图和折线图的复合图表，用于展示某公司在2017年至2020年期间的**递延收入（以百万美元计）**以及对应的**年度同比增长率（增速，%）**。\n\n### 图表结构与内容描述：\n\n#### 1. **横轴（X轴）**：\n- 表示年份，从2017年到2020年，共四个时间点。\n\n#### 2. **纵轴（Y轴）**：\n- 左侧纵轴表示**递延收入（单位：百万美元）**，数值范围从0到5000，刻度间隔为1000。\n- 右侧纵轴表示**增速（%）**，数值范围从0到35%，刻度间隔为5%。\n\n#### 3. **数据展示**：\n\n##### （1）橙色柱状图：递延收入（百万美元）\n- **2017年**：递延收入为 **2281.5 百万美元**\n- **2018年**：递延收入为 **2682.4 百万美元**\n- **2019年**：递延收入达到峰值，为 **3556.7 百万美元**\n- **2020年**：递延收入为 **4240.7 百万美元**\n\n> 注：虽然2020年递延收入继续上升，但增速已放缓。\n\n##### （2）红色折线图：增速（%）\n- **2017年**：无增速数据（起始年份，未显示）\n- **2018年**：增速为 **18%**\n- **2019年**：增速达到最高点，为 **33%**\n- **2020年**：增速回落至 **19%**\n\n#### 4. **趋势分析**：\n- **递延收入持续增长**：从2017年的2281.5百万美元增长至2020年的4240.7百万美元，整体呈现上升趋势，尤其在2019年和2020年增幅显著。\n- **增速先升后降**：增速在2019年达到顶峰（33%），2020年虽仍保持较高水平（19%），但较前一年有所下降，表明增长速度开始放缓。\n\n#### 5. **图例说明**：\n- 橙色柱形代表“递延收入（百万美元）”\n- 红色折线及圆点代表“增速（%）”\n\n---\n\n### 总结：\n该图清晰地展示了该公司在2017–2020年间递延收入的稳步增长态势，其中2019年是增长最迅猛的一年（增速达33%），而2020年尽管收入继续攀升至4240.7百万美元，但增速回落至19%，反映出业务扩张可能进入相对平稳阶段。",
        "metadata": {
            "filename": "广联达-公司深度报告开启新增长极-22022246页.pdf",
            "page": 42,
            "type": "image",
            "img_path": "images/06b5e55609bcc6b221549279edf8a884c274e5b8a18a9a7e17c5f8d0064bd22f.jpg",
            "table_body": "None"
        }
    },
    {
        "page_content": "标题为“图58 2018-2020年订阅收入及其增速”的图表，是一张结合了柱状图和折线图的复合图表，用于展示某公司在2017年至2020年间订阅收入的变化情况以及对应的同比增长率。\n\n具体描述如下：\n\n### 图表结构：\n- **横轴（X轴）**：表示年份，从2017年到2020年。\n- **纵轴（Y轴）**：包含两个刻度：\n  - 左侧纵轴表示“订阅收入（百万美元）”，范围从0到4,000；\n  - 右侧纵轴表示“增速（%）”，范围从0到120。\n\n### 数据内容：\n\n#### 柱状图（橙色柱体）——订阅收入（百万美元）：\n- **2017年**：订阅收入为894.3百万美元（即8.943亿美元）。\n- **2018年**：订阅收入上升至1802.3百万美元（即18.023亿美元）。\n- **2019年**：进一步增长至2751.9百万美元（即27.519亿美元）。\n- **2020年**：达到最高点，为3478.9百万美元（即34.789亿美元）。\n\n可以看出，订阅收入在2017年至2020年间持续快速增长。\n\n#### 折线图（红色折线）——增速（%）：\n- **2017年**：增速为102%（数据标注在折线上方）。\n- **2018年**：增速仍为102%（与2017年持平），表明2018年较2017年的增长率为102%。\n- **2019年**：增速下降至53%。\n- **2020年**：增速进一步下降至26%。\n\n这说明虽然订阅收入逐年增长，但增长率呈逐年放缓趋势。\n\n### 总结分析：\n该图表显示，在2017至2020年期间，公司订阅收入实现了显著增长，从约8.9亿美元增至约34.8亿美元。然而，尽管收入持续上升，其同比增长率却从102%逐步回落至26%，反映出增长势头虽强但增速有所减缓，可能进入成熟期或面临市场竞争加剧等挑战。\n\n此图可用于分析公司的业务成长性、市场扩张能力及未来增长潜力。",
        "metadata": {
            "filename": "广联达-公司深度报告开启新增长极-22022246页.pdf",
            "page": 42,
            "type": "image",
            "img_path": "images/8825b81a24cf8b6bf6f7d2e08cb36be5115cd68d97c9e311351d68a676e5c154.jpg",
            "table_body": "None"
        }
    },
    {
        "page_content": "这张图片是一张折线图，标题为“图59 转型后公司股价一路走高”，展示了某公司在2014年9月至2021年9月期间的股价走势。\n\n**图表内容详细描述如下：**\n\n- **坐标轴说明**：\n  - 横轴（X轴）表示时间，从2014年9月开始，以每年9月为节点，依次标注至2021年9月。\n  - 纵轴（Y轴）表示股价，单位未明确标出（可能是元或美元），数值范围从0到400，刻度间隔为50。\n\n- **数据曲线**：\n  - 图中有一条橙色折线，代表“股价”变化趋势。\n  - 从2014年9月起，股价大约在50左右波动，整体处于较低水平。\n  - 2015年至2017年期间，股价缓慢上升，但波动较小，基本维持在50至100之间。\n  - 2018年起，股价开始明显上行，进入增长通道。\n  - 2019年至2020年，股价持续攀升，突破200，并在2020年下半年达到约300以上。\n  - 2021年，股价一度冲高至接近350，随后出现小幅回调，但仍保持在较高水平。\n\n- **整体趋势**：\n  - 尽管早期增长缓慢，但从2018年开始，股价呈现显著上升趋势，尤其是在2020年之后加速上涨。\n  - 图表显示，在公司转型后（可能对应于2018年前后），股价表现出强劲的增长势头，符合标题所述“转型后公司股价一路走高”的判断。\n\n- **视觉特征**：\n  - 曲线平滑但有波动，反映出股价随市场和公司基本面变化而动态调整。\n  - 整体呈向上倾斜的趋势，尤其在2020年后斜率增大，显示出较高的增长动能。\n\n综上，该图通过清晰的时间序列展示了一家公司在经历转型后，其股价从低迷走向快速上涨的过程，反映了市场对公司发展前景的认可与信心增强。",
        "metadata": {
            "filename": "广联达-公司深度报告开启新增长极-22022246页.pdf",
            "page": 42,
            "type": "image",
            "img_path": "images/d45320befb13adf5e04176c8d946cb97ff0cb24bb616dca81d4e878266d21f8b.jpg",
            "table_body": "None"
        }
    },
    {
        "page_content": "Autodesk云转型战略的实施也获得了资本市场的认可。自2016 年2月1日实施部分永久许可停售以来，在公司的财务数据表现并不可观的情况下，公司股价一路走高，尤其自2016年8月1日宣布所有套件产品永久许可停售至今，公司股价进入了高速增长期。\n资料来源：Wind，首创证券\n",
        "metadata": {
            "filename": "广联达-公司深度报告开启新增长极-22022246页.pdf",
            "page": 42,
            "type": "text",
            "img_path": "None",
            "table_body": "None"
        }
    }
]