[
    {
        "page_content": "这张图片的标题为“图11：AI技术的应用可为公司带来收入增长和成本费用的降低”，是一张用于说明人工智能（AI）技术如何从收入和成本两个维度对公司产生积极影响的示意图。整体设计简洁明了，采用红、黄、白三色为主色调，通过箭头和文字框清晰地展示关键信息。\n\n图像分为上下两部分，分别对应“收入”和“成本费用”两大主题：\n\n---\n\n**上半部分：收入增长**\n\n左侧有一个红色矩形框，内写“收入”，表示该部分关注的是收入方面的提升。\n\n右侧有两个横向的红色条形框，每个框内有白色文字，并配有一个黄色向上的箭头，象征着增长趋势：\n\n1. **第一行**：  \n   - 内容：“现有产品：粘性、续费意愿”  \n   - 说明：AI技术可以增强现有产品的用户粘性和用户的续费意愿，从而提升客户留存率和长期收入。\n\n2. **第二行**：  \n   - 内容：“新功能、新模块：APRU”  \n   - 说明：通过AI开发新的功能或模块，能够提高每用户平均收入（Average Revenue Per User, APRU），即提升单个用户的收入贡献。\n\n这两项均指向“收入”的增加，强调AI在优化现有业务和拓展新增长点方面的双重作用。\n\n---\n\n**下半部分：成本费用降低**\n\n左侧同样有一个红色矩形框，内写“成本费用”，表示该部分关注的是成本控制与效率提升。\n\n右侧是一个横向的红色条形框，内部包含两个关键要素，由一个黄色向上箭头和一个向下箭头连接：\n\n- 左侧文字：“研发效率”  \n  - 配有黄色向上箭头，表示AI技术可以显著提升研发效率，加快产品迭代速度，减少试错成本。\n\n- 右侧文字：“相对研发投入”  \n  - 配有黄色向下箭头，表示尽管总体研发投入可能增加，但通过AI提升效率后，单位产出的研发投入（即“相对研发投入”）反而下降，实现成本优化。\n\n这表明AI不仅提升了研发产出，还降低了单位成本，从而实现“降本增效”。\n\n---\n\n**总结**：\n\n整张图通过直观的视觉语言展示了AI技术对企业的双轮驱动作用：\n- 在**收入端**：通过增强用户粘性、提升续费率以及推出高价值的新功能/模块来增加APRU；\n- 在**成本端**：通过提高研发效率，降低单位研发成本，实现相对研发投入的下降。\n\n这种“增收节支”的模式体现了AI技术在企业数字化转型中的核心价值。",
        "metadata": {
            "filename": "广联达-公司研究-大模型助力智慧建筑未来可期新成本产品加倍云收入空间-23032619页.pdf",
            "page": 9,
            "type": "image",
            "img_path": "images/1710d897f5417e44451f57d1f9e35fc4ba5e60f94a2bb0a779b4257f1f806a33.jpg",
            "table_body": "None"
        }
    },
    {
        "page_content": "# 2 远期业绩超预期：新成本业务有望打开公司长期成长空间\n行业增速下行和房住不炒背景下，提升建筑品质、优化建造成本、提升效益成为企业生存的必然选择。根据 CRIC，金额方面，57 家典型上市房企2021 年整体营业收入3.91万亿（ $+ 1 6 \\%$ ），增速持续下滑，毛利润0.78亿元、归母净利润0.26万亿，归母净利润增速的中位数为 $- 2 6 \\%$ ；比率方面，2018-2021年整体毛利率持续下降，中位数从 $3 1 . 2 \\%$ 降至$1 9 . 3 \\%$ ，带动归母净利率中位数从 $1 2 . 1 \\%$ 降至 $4 . 7 \\%$ 。\n数字新成本平台有望系统化解决企业造价数据积累和应用难题。该平台面向企业精细化管理的诉求，针对建设方、施工方分别搭建了以企业成本数据积累与应用的闭环打通为核心的解决方案，赋能企业实现数据资产化、作业高效化、决策智能化，能够助力企业实现“目标估（定）得准、过程控得住”。\n",
        "metadata": {
            "filename": "广联达-公司研究-大模型助力智慧建筑未来可期新成本产品加倍云收入空间-23032619页.pdf",
            "page": 9,
            "type": "text",
            "img_path": "None",
            "table_body": "None"
        }
    }
]