[
    {
        "page_content": "# 图表目录\n图 1：2023 年中国数据分析和人工智能技术成熟度曲线……6  \n图2：我国建筑业总产值和同比增速（万亿元， $\\%$ ) …….6  \n图3：我国建筑工程项目成本占收入大致构成 $1 \\%$ )……7  \n图 4：建筑行业项目超时和费用超标已成常态….. ……7  \n图5：我国建筑业的长期优势…… …7  \n图6：我国数字经济规模（万亿元、 $\\%$   \n图7：我国数字经济规模占GDP比重 $( \\%$ ) 8  \n图8：我国数字经济内部结构 $( \\% )$   \n图9：二十大报告对我国产业数字化转型的布局….. …8  \n图10：我国建筑行业信息化渗透率情况 $( \\%$ ) …….8  \n图11：我国建筑业工人年龄分布 $( \\%$ ) …… 9  \n图12：我国建筑业工人学历分布 $( \\%$ 9  \n图13：广联达施工业务发展路径... …… ……9  \n图14：广联达施工业务历史沿革. … 10  \n图15： 广联达 2022 年收入构成 $( \\%$ )…… 10  \n图16： 广联达工程施工收入及其变化率（亿元， $\\%$ ) . 10  \n图 17：广联达建筑业务平台战略……11  \n图 18：广联达物资项企一体化解决方案…… 12  \n图19： 广联达物资项企一体化解决方案价值体系 …. 12  \n图 20：公司智能物料验收系统产品形态… 13  \n图 21：公司智能物料验收系统核心功能….  \n图22： 地磅系统真实记录.. ….13  \n图23: 智能物料验收系统实现全方位物料管控.. ….1  \n图24： 支持云计划模板…… … 14  \n图25： 线上查看项目进度…… … 14  \n图26：时间 $^ +$ 空间全方位进度规划， .1 4  \n图27： 关键线路动态管理.. … ….14  \n图28： 广联达智慧工地……… 15  \n图29：公司智慧塔吊管理系统… ……. 15  \n图30：塔基检测系统… 16  \n图 31：精确记录每一次塔吊运行… 16  \n图 32：公司B劳务管理系统 …… 16  \n图 33：AI识别规范安全作业.. …. 7  \n图 34：人脸识别实现实名制管理……17  \n图 35：从进场开始控制用工风险…… 17  \n图36：全流程控制人力成本 …. 17  \n图37： 劳务管理系统赋能企业……. … 17  \n图 38：面向工程建设领域企业客户的新 PaaS 平台 …18  \n图 39：市场拓展全在线，助力扩大开源，智能风控前置…. 18  \n图40：PMCore 云项目管理解决方案… 18  \n图 41：企业管理者，足不出户项目进度情况一目了然……19  \n图 42：我国建筑业产值分布情况（亿元）… 19\n",
        "metadata": {
            "filename": "广联达-公司深度报告四小龙有望成为施工百亿市场增长引擎-24050531页.pdf",
            "page": 3,
            "type": "text",
            "img_path": "None",
            "table_body": "None"
        }
    }
]