[
    {
        "page_content": "这张图片展示了一个关于**数据驱动企业全价值链闭环模型**的示意图，来源于“广联达2020年投资者大会演示文稿”，由申港证券研究所整理。整体内容分为两部分：左侧是一个循环流程图，右侧是四个步骤的详细说明。\n\n---\n\n### **一、左侧图形结构（核心循环模型）**\n\n这是一个以“用户”为中心的四维闭环系统，围绕用户展开“研、营、销、服”四大业务环节，并通过“应用”、“数据”和“算法”三个关键要素形成正向循环。\n\n- **中心节点**：  \n  - 中央橙色圆圈标注为“**用户**”，代表整个体系的核心。\n\n- **四个外围节点**（按顺时针方向）：\n  1. **研**（研发）：位于上方，表示产品研发。\n  2. **营**（营销）：位于右侧，表示市场推广与客户获取。\n  3. **销**（销售）：位于下方，表示产品销售与服务交付。\n  4. **服**（服务）：位于左侧，表示售后服务与用户体验支持。\n\n- **连接关系**：\n  - 各环节之间通过箭头连接，构成一个闭环流程：\n    - “研” → “营” → “销” → “服” → “研”，体现从研发到服务再反馈至研发的完整生命周期。\n  - 在每个环节与“用户”之间有双向交互路径，强调用户在各阶段中的参与和影响。\n  - 三条关键连接线分别标注了：\n    - **应用**：连接“研”与“服”，表示软件/硬件功能的应用体验。\n    - **数据**：连接“营”与“服”，表示用户行为数据的采集与流动。\n    - **算法**：连接“销”与“研”，表示数据分析结果反哺研发优化。\n\n---\n\n### **二、右侧文字说明（四个阶段）**\n\n右侧分为四个橙色标题框，每个框对应一个发展阶段，详细解释该闭环模型的运行逻辑：\n\n#### **1、应用产生数据**\n> 软硬件的功能应用体验越好，用户粘性越强，产生的用户行为数据越多。\n\n- 解释：优质的产品和服务能提升用户体验，从而吸引用户持续使用，生成大量真实的行为数据。\n- 核心观点：好的应用是数据积累的基础。\n\n#### **2、数据优化算法**\n> 不同场景的数据积累越多，对用户真实使用情况、不同类型用户的特点，以及背后需求的理解越深刻，结合业务的数据分析模型和算法持续优化。\n\n- 解释：随着数据量的增长，企业可以更精准地理解用户画像和行为模式，进而改进算法模型，提升预测能力和个性化服务能力。\n- 核心观点：数据是算法迭代的关键输入。\n\n#### **3、算法提升应用**\n> 更好的算法进一步提升应用的智能化，让产品更好用、更有用，提升价值和用户体验。\n\n- 解释：经过优化的算法被重新应用于产品中，使应用更加智能高效，例如自动化推荐、智能预警等，增强产品的竞争力。\n- 核心观点：算法升级推动应用进化。\n\n#### **4、数据驱动全价值链**\n> 以用户为中心，以数据为驱动。研营销服从过去的串联变成并联，数字化带来精准化，提升全价值链效率。\n\n- 解释：最终目标是实现“研、营、销、服”四大环节的协同联动，不再线性推进，而是基于数据进行并行决策与快速响应，全面提升企业运营效率。\n- 核心观点：构建以数据为核心的数字化闭环，实现全链条的智能化管理。\n\n---\n\n### **三、整体逻辑总结**\n\n该图描绘的是一个**“数据-算法-应用-用户”正向反馈闭环**，其本质是：\n\n> **用户使用优质应用 → 产生高质量数据 → 数据训练优化算法 → 算法赋能应用升级 → 提升用户体验 → 吸引更多用户使用……**\n\n这个循环不断迭代，推动企业从传统模式向**数据驱动型组织**转型，实现**全价值链的数字化、智能化升级**。\n\n---\n\n### **四、应用场景与意义**\n\n此模型适用于互联网、SaaS、智能硬件、金融科技等行业，尤其适合像广联达这样的**企业级软件服务商**，强调通过用户数据沉淀和技术能力迭代，打造可持续增长的商业生态。\n\n---\n\n### **五、资料来源标注**\n\n图片右下角注明：“资料来源：广联达2020年投资者大会演示文稿，申港证券研究所”，表明这是在资本市场分析中用于解读公司战略发展路径的重要参考框架。\n\n--- \n\n✅ 总结一句话：  \n这是一张描述**以用户为中心、数据为驱动、算法为引擎、应用为载体**的企业全价值链闭环发展的战略示意图，展现了数字化时代企业如何通过“研-营-销-服”协同运作实现持续创新与增长。",
        "metadata": {
            "filename": "广联达-造价筑底施工决胜-22041233页.pdf",
            "page": 15,
            "type": "image",
            "img_path": "images/fe7b2c738dfd1895a3e7073ce8c40c2af44d15345e0de2a1eb4a0c7b23933bc6.jpg",
            "table_body": "None"
        }
    },
    {
        "page_content": "预期到 2025 年，数字造价总体市场规模将接近 90 亿元，广联达云收入有望超过 65亿元。\n# 市场端假设：\n根据工程造价事业发展十三五规划中公布的数据，截至十二五末（2015 年末），我国从事工程造价的专业技术人员数量达到145万。另据工程造价咨询统计公报，2015 年-2020 年末，我国在专业工程造价咨询机构从事造价工作的专业技术人数从28.3 万人增加至47.3万人。假定以同等比例推算全国总的造价专业技术人员数量，则预计2020 年末全国范围内造价专业技术人员约 240 万人，假定该数量之后以每年 $5 \\%$ 的增速增加。  \n考虑部分高级的造价技术人员不再亲自使用软件进行建模算量等基础工作，同时企业购置软件往往是根据软件资源动态分配下的使用峰值确定需求而非依据实际的技术员工数，因此假定专业人员数量与造价软件的需求数比例为2：1。  \n考虑盗版用户的逐步转化，依据广联达披露的 2019 年用户正盗版用户比例，假定市场中2020年正版用户比例约 $60 \\%$ ，至2025年正版率提升至 $80 \\%$ o  \n根据广联达2020 年11 月的投资者关系活动调研纪要，当时其造价软件客单价为4000-5000 元。假定市场总体的软件的订阅价格 2020 年为 4500 元，之后每年按$10 \\%$ 的增长率计算。\n# 广联达造价收入端假定：\n假定数字造价业务随着云转型完成收入增长逐步趋缓，未来4 年增长率$2 3 \\% / 2 1 \\% / 1 9 \\% / 1 7 \\%$ 。  \n假定云业务收入占比继续上升，2022 年达到 $7 5 \\%$ ，并逐步上升至2025 年的 $8 5 \\%$ 。  \n$\\bullet$ 假定转型期中的 2020-2022 年，广联达数字造价非云业务营收分别依 $50 \\%$ $2 5 \\%$ $10 \\%$ 的比例还原于为云业务收入用于测算和比较。\n",
        "metadata": {
            "filename": "广联达-造价筑底施工决胜-22041233页.pdf",
            "page": 15,
            "type": "text",
            "img_path": "None",
            "table_body": "None"
        }
    }
]