[
    {
        "page_content": "这张图片是一张柱状图，标题为“图56、经销商数量逐年稳步增长”，用于展示某企业在2017年至2020年期间经销商数量的变化趋势。\n\n图表的横轴表示年份，从左到右依次为2017年、2018年、2019年和2020年；纵轴表示经销商数量（单位：家），数值范围从0到1000，以100为间隔进行标注。\n\n具体数据如下：\n- 2017年，经销商数量为521家；\n- 2018年，增长至606家；\n- 2019年，进一步增加到748家；\n- 2020年，达到907家。\n\n每个年份对应一个蓝色的竖直柱子，柱子的高度随年份递增而明显上升，反映出经销商数量持续且稳定的增长态势。图例中用蓝色方块标注“经销商数量（家）”，表明柱状图所代表的数据内容。\n\n整体来看，该图清晰地展示了该公司在四年间经销商网络的快速扩张，体现了其市场拓展能力的增强和渠道布局的不断深化。",
        "metadata": {
            "filename": "千味央厨-厨之道央泱食材中有千味结-21090631页.pdf",
            "page": 25,
            "type": "image",
            "img_path": "images/5e2528ead005ac474e53ff976facce031c7d567ab7b4955f9ce31615e7400fd8.jpg",
            "table_body": "None"
        }
    },
    {
        "page_content": "这张图片是**图 57**，标题为“**截止 2020 年，经销商体量分布情况**”，是一张柱状图，用于展示从2017年到2020年期间，不同规模经销商在整体经销商群体中的占比情况。图表通过四组并列的柱状图分别表示每年四个不同销售额区间的经销商所占比例。\n\n### 图表基本信息：\n- **横轴（X轴）**：表示年份，分别为2017、2018、2019和2020年。\n- **纵轴（Y轴）**：表示占比，范围从0.00%到60.00%，以10%为单位递增。\n- **图例说明**：\n  - 深蓝色（■）代表“500万元以上”销售额的经销商；\n  - 红色（■）代表“100-500万元”销售额的经销商；\n  - 浅蓝色（■）代表“10-100万元”销售额的经销商；\n  - 粉色（■）代表“10万元以下”销售额的经销商。\n\n---\n\n### 各年份具体数据描述：\n\n#### **2017年**\n- “500万元以上”：约2.5%\n- “100-500万元”：约15%\n- “10-100万元”：约40%\n- “10万元以下”：约41%\n\n> 此年份中，“10万元以下”和“10-100万元”两类经销商占比最高，合计超过80%。\n\n#### **2018年**\n- “500万元以上”：约3%\n- “100-500万元”：约12%\n- “10-100万元”：约45%\n- “10万元以下”：约39%\n\n> “10-100万元”类经销商占比略有上升，达到最高点之一；“10万元以下”占比小幅下降。\n\n#### **2019年**\n- “500万元以上”：约2.5%\n- “100-500万元”：约13%\n- “10-100万元”：约43%\n- “10万元以下”：约40%\n\n> 整体结构与2018年相近，各区间变化不大，保持稳定趋势。\n\n#### **2020年**\n- “500万元以上”：约2%\n- “100-500万元”：约12%\n- “10-100万元”：约51%\n- “10万元以下”：约34%\n\n> 这一年显著变化在于：“10-100万元”类经销商占比首次突破50%，成为最大群体；而“10万元以下”类占比明显下降至34%。\n\n---\n\n### 总结分析：\n- **趋势观察**：\n  - “10-100万元”规模的经销商占比逐年上升，从2017年的40%增长至2020年的51%，表明中等规模经销商在整体渠道结构中逐渐占据主导地位。\n  - “10万元以下”的小型经销商占比呈缓慢下降趋势，从2017年的41%降至2020年的34%。\n  - “500万元以上”和“100-500万元”两个高规模层级占比始终较低且波动不大，维持在2%-15%之间，说明大型经销商数量相对较少。\n\n- **结论**：\n  截止2020年，该企业或行业的经销商体系以**中等规模（10-100万元）为主力**，小规模经销商仍占较大比重但正在被逐步优化或整合，而大中型经销商（尤其是500万以上）仍属少数。这可能反映出企业在渠道管理上正向更高效、更具市场竞争力的中型经销商倾斜。",
        "metadata": {
            "filename": "千味央厨-厨之道央泱食材中有千味结-21090631页.pdf",
            "page": 25,
            "type": "image",
            "img_path": "images/2e7b2b4170c72a06d8ce89d84533e31395345f23227fcc16590fa0f024e7df0e.jpg",
            "table_body": "None"
        }
    },
    {
        "page_content": "这张图表的标题为“图58、公司前五大直营客户体量上升，占比下降（单位：万元，%）”，是一张**复合柱状图与折线图结合的统计图表**，用于展示某公司在2017年至2020年期间，其前五大直营客户的收入构成情况以及这些客户在公司总收入中的占比变化趋势。\n\n---\n\n### **一、整体结构**\n\n- **横轴（X轴）**：表示年份，分别为2017、2018、2019、2020年。\n- **纵轴（左轴）**：表示收入金额，单位为**万元**，范围从0到35,000万元。\n- **纵轴（右轴）**：表示**百分比**，范围从0%到100%，用于显示两个关键比例：\n  - 前五大直营客户占**直营收入**的比重（红色折线）\n  - 前五大直营客户占**总营业收入**的比重（绿色折线）\n\n---\n\n### **二、柱状图内容（按颜色区分）**\n\n每个年份的柱状图由多个颜色堆叠组成，代表不同直营客户贡献的收入，具体如下：\n\n| 颜色 | 客户名称 |\n|------|----------|\n| 深蓝色 | 百胜 |\n| 浅蓝色 | 永和 |\n| 青色 | 真功夫 |\n| 灰色 | 海底捞 |\n| 红色 | 华莱士 |\n| 粉色 | 九毛九 |\n| 橙色 | 富士康 |\n\n#### **各年度收入构成分析**：\n\n1. **2017年**\n   - 总收入约21,000万元\n   - 百胜占比最大（约36.75%），是主要客户\n   - 其他客户如永和、真功夫、海底捞等贡献较小\n\n2. **2018年**\n   - 总收入上升至约25,000万元\n   - 百胜仍为主力，占比36.38%\n   - 各客户收入均有增长，但百胜仍是主导\n\n3. **2019年**\n   - 收入进一步增至约30,000万元\n   - 百胜占比略降至36.08%\n   - 华莱士、九毛九等客户收入有所提升，但整体仍以百胜为核心\n\n4. **2020年**\n   - 收入约为29,000万元（略有回落）\n   - 百胜占比显著下降至**31.13%**\n   - 其他客户如华莱士、九毛九、富士康等份额相对上升\n\n> ✅ **结论**：尽管前五大直营客户的**总营收体量逐年上升**（从2017年的约2.1亿增至2019年的近3亿），但其在公司整体收入中的**占比呈现下降趋势**。\n\n---\n\n### **三、折线图内容（右轴）**\n\n1. **红色折线（占直营收入比重）**\n   - 表示前五大直营客户在**直营收入中所占的比例**\n   - 2017年：90.60%\n   - 2018年：89.47%\n   - 2019年：88.03%\n   - 2020年：87.30%\n   - 趋势：**逐年缓慢下降**，说明直营业务中非前五大客户的贡献在增加\n\n2. **绿色折线（占营业收入比重）**\n   - 表示前五大直营客户在公司**全部营业收入**中的占比\n   - 该线基本保持平稳，略呈下降趋势，维持在约40%-45%之间\n   - 说明虽然前五大客户收入增长，但公司整体收入来源更加多元化\n\n---\n\n### **四、核心结论解读**\n\n- **“体量上升”**：前五大直营客户合计收入从2017年的约2.1亿元增长到2019年的近3亿元，表明这些大客户对公司业务的重要性仍在增强。\n- **“占比下降”**：\n  - 在**直营收入中**，前五大客户占比从90.6%降至87.3%，说明公司正在拓展更多中小型直营客户或渠道。\n  - 在**总营业收入中**，占比也趋于稳定甚至微降，反映公司收入结构正逐步优化，不再过度依赖少数头部客户。\n\n---\n\n### **五、总结**\n\n该图通过数据直观展示了公司在发展过程中，**既保持了与大型直营客户的合作关系，又实现了客户结构的多样化**。尽管前五大客户收入持续增长，但其在整体收入中的权重下降，反映出公司经营策略的成熟与抗风险能力的提升。",
        "metadata": {
            "filename": "千味央厨-厨之道央泱食材中有千味结-21090631页.pdf",
            "page": 25,
            "type": "image",
            "img_path": "images/2f8dd76d0687026e6cad238480fa84e3eee3af8b27b5e3e33f2d6bb150ecb4df.jpg",
            "table_body": "None"
        }
    },
    {
        "page_content": "# 大客户稳定度高，商超客户补充增量。\n直营占比稳定。公司2020年直营渠道收入为3.37亿元，占主营收入的 $3 5 . 7 4 \\%$ ,占比稳定得益于公司较好的产品品质及较高的客户认可度。2020 年直营客户收入占比下降，主要系疫情影响下，百胜中国旗下肯德基、必胜客门店因餐厅暂时停业、营业时间缩短及客流减少导致对千味央厨产品的采购额减少。大客户合作特点：长期且稳定。2020 年公司前五大直营客户贡献收入占比$3 1 . 1 3 \\%$ ，占比保持稳定。公司前五大直营客户为百胜中国、华莱士、九毛九、真功夫、海底捞等大型知名连锁餐饮企业，其中百胜中国为第一大直营客户，占比收入比重 $2 3 . 4 2 \\%$ ，2016年与公司签订长期有效合同，稳定性强。2018年，公司百胜旗下肯德基研发上新7支单品。\n商超作为补充增量渠道。相较于传统商超C端销售模式，公司与商超客户合作的差异性主要体现在：1）公司向商超的销售均为买断式销售，商超按其销售定价自行对外销售；2）商超需拆除产品包装，并经过二次加工后在其熟食区销售；3）商超以其自身名义对外销售，消费者并不了解其上游供应商。\n",
        "metadata": {
            "filename": "千味央厨-厨之道央泱食材中有千味结-21090631页.pdf",
            "page": 25,
            "type": "text",
            "img_path": "None",
            "table_body": "None"
        }
    }
]